Workbook

Sheet Tab 1 – Assumptions
A1: APEX TECHNOLOGY CORPORATION — ASSUMPTIONS & SOURCE DATA
A2: All hardcoded case facts live here. Build every downstream calculation with cell links; do not embed case numbers in formulas.
A4: MODEL CONVENTIONS | F4: HYPOTHETICAL TECH VALUATION & IPO INPUTS
A5: Item | B5: Value | C5: Units | D5: Calculation note | F5: Assumption | G5: Value | H5: Use in model
A6: Company | B6: Apex Technology Corporation | C6: Fictional case | F6: Next-year dividend (D₁) | G6: 0.84 | H6: DDM numerator
A7: Financial period | B7: Fiscal year ended Dec 31 | C7: Annual | F7: Required return on equity | G7: 0.105 | H7: DDM discount rate
A8: Model scale | B8: $ in thousands; shares in thousands | C8: Consistent units | D8: Per-share outputs remain dollars per share | F8: Perpetual dividend growth | G8: 0.04 | H8: DDM growth rate
A9: Income tax rate | B9: 0.25 | C9: % | D9: Applied to positive pre-tax income | F9: Year 1 FCFF | H9: Calculate in Tab 2 B56; not supplied
A10: Short-term debt rate | B10: 0.12 | C10: % | F10: WACC | G10: 0.09 | H10: FCFF discount rate
A11: Long-term debt rate | B11: 0.12 | C11: % | F11: Long-run FCFF growth | G11: 0.04 | H11: FCFF growth rate
A12: Tie-out tolerance | B12: 1 | C12: $000s | D12: Rounding threshold for dollar checks | F12: Peer P/E | G12: 18
A13: Per-share tolerance | B13: 0.01 | C13: $ / share | D13: Rounding threshold for per-share checks | F13: Peer P/S | G13: 2.2
A14: Immediate EV recognition for capex | B14: 1 | C14: % | D14: Simplified case: deployed capital enters EV dollar-for-dollar at closing | F14: Proposed IPO price | G14: 20 | H14: Primary offering price per share
F15: New primary shares issued | G15: 20000 | H15: Shares in thousands
A16: PRE-IPO INCOME STATEMENT | F16: Stated gross proceeds | G16: 400000 | H16: $000s
A17: Line item | B17: Value | C17: Units | D17: Calculation note | F17: IPO issuance fees | G17: 0 | H17: $000s; simplified case, explicitly modeled
A18: Revenue | B18: 850000 | C18: $000s | F18: Net proceeds | G18: =G16-G17 -> 400000 | H18: Gross proceeds less fees
A19: Cost of goods sold | B19: 255000 | C19: $000s | F19: Pre-IPO shares | G19: 50000 | H19: Shares in thousands
A20: Gross profit | B20: =B18-B19 -> 595000 | C20: $000s | D20: Revenue less cost of goods sold | F20: Post-IPO shares | G20: =G19+G15 -> 70000 | H20: Pre-IPO plus new shares
A21: Operating expenses | B21: 340000 | C21: $000s | D21: SG&A plus R&D | F21: Gross proceeds check | G21: =G14*G15-G16 -> 0 | H21: Price × new shares less stated gross proceeds
A22: EBIT | B22: =B20-B21 -> 255000 | C22: $000s | D22: Gross profit less operating expenses
A23: Interest expense | B23: =B36*B10+B37*B11 -> 36000 | C23: $000s | D23: Debt balance times stated rates | F23: SCENARIO DEPLOYMENT ASSUMPTIONS
A24: Earnings before tax | B24: =B22-B23 -> 219000 | C24: $000s | D24: EBIT less interest expense | F24: Use of net proceeds | G24: Scenario A | H24: Scenario B | I24: Scenario C
A25: Income tax | B25: =B24*B9 -> 54750 | C25: $000s | D25: Earnings before tax times tax rate | F25: Scenario label | G25: Maximum debt reduction | H25: Growth investment | I25: Balanced mix
A26: Net income | B26: =B24-B25 -> 164250 | C26: $000s | D26: Earnings before tax less income tax | F26: Debt repayment | G26: 300000 | H26: 0 | I26: 200000
F27: Growth capex / operating assets | G27: 0 | H27: 400000 | I27: 200000
A28: PRE-IPO BALANCE SHEET | F28: Cash retained | G28: 100000 | H28: 0 | I28: 0
A29: Line item | B29: Value | C29: Units | D29: Calculation note | F29: Total uses | G29: =SUM(G26:G28) -> 400000 | H29: =SUM(H26:H28) -> 400000 | I29: =SUM(I26:I28) -> 400000
A30: Cash & equivalents | B30: 45000 | C30: $000s | F30: Sources & uses check | G30: =$G$18-G29 -> 0 | H30: =$G$18-H29 -> 0 | I30: =$G$18-I29 -> 0
A31: Accounts receivable | B31: 120000 | C31: $000s | F31: Rationale | G31: Repay all existing debt; retain excess cash | H31: Fund operating assets; retain existing debt | I31: Reduce leverage while funding growth
A32: Inventory | B32: 35000 | C32: $000s
A33: Property, plant & equipment | B33: 280000 | C33: $000s
A34: Intangibles & goodwill | B34: 150000 | C34: $000s
A35: Accounts payable | B35: 85000 | C35: $000s
A36: Short-term debt | B36: 60000 | C36: $000s | F36: COLOR & FORMULA LEGEND
A37: Long-term debt | B37: 240000 | C37: $000s | F37: Yellow fill + blue text | G37: Student build cell | H37: Enter a formula or written response
A38: Common equity | B38: 245000 | C38: $000s | F38: Gray fill + black text | G38: Provided assumption | H38: Reference; do not retype downstream
A39: Total current assets | B39: =SUM(B30:B32) -> 200000 | C39: $000s | D39: Cash plus receivables plus inventory | F39: Green text | G39: Linked formula output | H39: Use only after the related formula is built
A40: Total debt | B40: =SUM(B36:B37) -> 300000 | C40: $000s | D40: Short-term plus long-term debt
A41: Total liabilities | B41: =B35+B40 -> 385000 | C41: $000s | D41: Accounts payable plus total debt
A42: Total assets | B42: =B39+B33+B34 -> 630000 | C42: $000s | D42: Current assets plus PP&E plus intangibles
A43: Total liabilities & equity | B43: =B41+B38 -> 630000 | C43: $000s | D43: Total liabilities plus common equity
A44: Balance sheet check | B44: =B42-B43 -> 0 | C44: $000s | D44: Total assets less liabilities and equity; must equal zero
A46: PRE-IPO TECH SCENARIO: HYPOTHETICAL YEAR 1 OPERATING INPUTS
A47: Teaching assumptions for a mature dividend-paying tech company. Value immediately before the IPO. Assume stable growth from Year 1, constant rates, and all existing cash is excess cash. These are fictional scenario inputs, not market estimates.
A49: Year 1 input | B49: Value | C49: Units | D49: Scenario assumption
A50: EBIT | B50: 255000 | C50: $000s | D50: Flat EBIT versus case history | F50: DDM assumes D1 = $0.84, cost of equity = 10.5%, and dividend growth = 4%. FCFF assumes WACC = 9% and growth = 4%. Evaluate payout capacity and reinvestment needs before treating either model as credible.
A51: Depreciation & amortization | B51: 30000 | C51: $000s | D51: Noncash expense included in EBIT
A52: Recurring operating capex | B52: 150000 | C52: $000s | D52: Pre-IPO operating investment; excludes IPO-funded projects
A53: Increase in operating NWC | B53: 19250 | C53: $000s | D53: Cash investment; excludes cash and debt

Sheet Tab 2 – Valuation
A1: APEX TECHNOLOGY CORPORATION — PRE-IPO EQUITY VALUATION
A2: Required: calculate Year 1 FCFF in B50:B56, link F6 to B56, then build DDM B11 and FCFF F13:F15. Use existing debt, cash, and 50M pre-IPO shares. Compare with the $20 proposed offer.
A4: PART A — DIVIDEND DISCOUNT MODEL | E4: PART B — FREE CASH FLOW TO FIRM
A5: Input / output | B5: Value | C5: Units | D5: Formula logic | E5: Input / output | F5: Value | G5: Units | H5: Formula logic
A6: Next-year dividend (D₁) | C6: $ / share | D6: Link to assumptions | E6: Projected FCFF — Year 1 | G6: $000s | H6: Link to calculated FCFF
A7: Required return (r) | C7: % | D7: Link to assumptions | E7: WACC | F7: ='Tab 1 – Assumptions'!$G$10 -> 0.09 | G7: % | H7: Link to assumptions
A8: Perpetual growth (g) | C8: % | D8: Link to assumptions | E8: Perpetual FCFF growth | F8: ='Tab 1 – Assumptions'!$G$11 -> 0.04 | G8: % | H8: Link to assumptions
A9: DDM denominator | C9: % | D9: Required return less growth | E9: Total debt | F9: ='Tab 1 – Assumptions'!$B$40 -> 300000 | G9: $000s | H9: Link to assumptions
E10: Cash | F10: ='Tab 1 – Assumptions'!$B$30 -> 45000 | G10: $000s | H10: Link to assumptions
A11: DDM value per share | C11: $ / share | D11: D1 divided by (r − g); r must exceed g | E11: Pre-IPO shares | F11: ='Tab 1 – Assumptions'!$G$19 -> 50000 | G11: 000s shares | H11: Link to assumptions
E12: FCFF denominator | F12: =F7-F8 -> 0.05 | G12: % | H12: WACC less growth
E13: Enterprise value | G13: $000s | H13: FCFF₁ divided by (WACC − g)
E14: Pre-money equity value | G14: $000s | H14: Enterprise value less debt plus cash
E15: FCFF value per pre-IPO share | G15: $ / share | H15: Pre-money equity value divided by pre-IPO shares
A18: PART C — RELATIVE VALUATION
A19: Input | B19: Value | C19: Units | D19: Calculation note | E19: Student calculation | F19: Value | G19: Units | H19: Formula logic
A20: Pre-IPO net income | C20: $000s | D20: Link to assumptions | E20: Earnings per share | G20: $ / share | H20: Net income divided by pre-IPO shares
A21: Pre-IPO shares | C21: 000s shares | D21: Link to assumptions | E21: P/E implied price | G21: $ / share | H21: EPS times peer P/E
A22: Revenue | C22: $000s | D22: Link to assumptions | E22: Revenue per share | G22: $ / share | H22: Revenue divided by pre-IPO shares
A23: Peer P/E | C23: x | D23: Link to assumptions | E23: P/S implied price | G23: $ / share | H23: Revenue per share times peer P/S
A24: Peer P/S | C24: x | D24: Link to assumptions
A27: PART D — VALUATION COMPARISON & INTERPRETATION
A28: Method | B28: Implied value / share | C28: Proposed offer | D28: Premium / (discount) to model | E28: Interpretation / reliability
A29: DDM | C29: ='Tab 1 – Assumptions'!$G$14 -> 20
A30: FCFF | C30: ='Tab 1 – Assumptions'!$G$14 -> 20
A31: Peer P/E | C31: ='Tab 1 – Assumptions'!$G$14 -> 20
A32: Peer P/S | C32: ='Tab 1 – Assumptions'!$G$14 -> 20
A35: VALUATION CHECKS
A36: Check | B36: Status | C36: Delta / condition | D36: What it tests
A37: DDM denominator | B37: =IF(B11="","BUILD",IF(B7>B8,"PASS","CHECK")) -> BUILD | C37: =B9 -> 0 | D37: Required return must exceed perpetual growth
A38: FCFF denominator | B38: =IF(F13="","BUILD",IF(F7>F8,"PASS","CHECK")) -> BUILD | C38: =F12 -> 0.05 | D38: WACC must exceed perpetual growth
A39: Offer proceeds | B39: =IF(ABS('Tab 1 – Assumptions'!$G$21)<='Tab 1 – Assumptions'!$B$12,"PASS","CHECK") -> PASS | C39: ='Tab 1 – Assumptions'!$G$21 -> 0 | D39: Offer price × new shares agrees with stated gross proceeds
A40: FCFF equity bridge | B40: =IF(F14="","BUILD",IF(ABS(F14-(F13-F9+F10))<='Tab 1 – Assumptions'!$B$12,"PASS","CHECK")) -> BUILD | C40: =IF(F14="","",F14-(F13-F9+F10)) | D40: EV less debt plus cash equals pre-money equity value
A46: REQUIRED FIRST STEP — CALCULATE YEAR 1 FCFF
A47: Use the hypothetical Year 1 inputs from Tab 1 rows 50–53 and tax rate B9. Add back D&A and subtract operating investment. Exclude interest, debt repayment, IPO proceeds, and IPO-funded capex.
A49: Cash-flow build | B49: Value | C49: Units | D49: Formula logic
A50: Year 1 EBIT | C50: $000s | D50: Link to assumptions
A51: Tax rate | C51: % | D51: Link to assumptions
A52: NOPAT | C52: $000s | D52: EBIT × (1 − tax rate)
A53: Add: D&A | C53: $000s | D53: Link to assumptions
A54: Less: operating capex | C54: $000s | D54: Link to assumptions
A55: Less: increase in operating NWC | C55: $000s | D55: Link to assumptions
A56: Year 1 FCFF | C56: $000s | D56: NOPAT + D&A − capex − increase in NWC
A58: Required interpretation: explain why DDM and FCFF produce different prices. Assess the assumed dividend policy, cash conversion, and perpetual growth. State whether the $20 offer is supported under these assumptions. Do not average the models automatically.

Sheet Tab 2a – Earnings
A1: APEX TECHNOLOGY CORPORATION — SCENARIO EARNINGS
A2: Build each scenario income statement from operating assumptions and post-transaction debt. Interest savings change taxes, net income, and EPS.
A4: PRE-IPO AND POST-IPO SCENARIO EARNINGS
A5: Line item | B5: Pre-IPO | C5: Scenario A | D5: Scenario B | E5: Scenario C | F5: Formula logic
A6: Revenue | B6: ='Tab 1 – Assumptions'!$B$18 -> 850000 | F6: Link to the same operating case
A7: Cost of goods sold | B7: ='Tab 1 – Assumptions'!$B$19 -> 255000 | F7: Link to the same operating case
A8: Gross profit | B8: =B6-B7 -> 595000 | F8: Revenue less cost of goods sold
A9: Operating expenses | B9: ='Tab 1 – Assumptions'!$B$21 -> 340000 | F9: Link to the same operating case
A10: EBIT | B10: =B8-B9 -> 255000 | F10: Gross profit less operating expenses
A11: Short-term debt | B11: ='Tab 1 – Assumptions'!$B$36 -> 60000 | F11: Pay down short-term debt first
A12: Long-term debt | B12: ='Tab 1 – Assumptions'!$B$37 -> 240000 | F12: Then apply remaining repayment to long-term debt
A13: Interest expense | B13: =B11*'Tab 1 – Assumptions'!$B$10+B12*'Tab 1 – Assumptions'!$B$11 -> 36000 | F13: Debt balances times stated rates
A14: Earnings before tax | B14: =B10-B13 -> 219000 | F14: EBIT less interest expense
A15: Income tax | B15: =B14*'Tab 1 – Assumptions'!$B$9 -> 54750 | F15: EBT times tax rate
A16: Net income | B16: =B14-B15 -> 164250 | F16: EBT less tax
A17: Shares outstanding | B17: ='Tab 1 – Assumptions'!$G$19 -> 50000 | F17: Pre shares before; diluted post shares after
A18: Earnings per share | B18: =B16/B17 -> 3.285 | F18: Net income divided by shares
A21: EARNINGS AUDIT
A22: Check | B22: Pre-IPO | C22: Scenario A | D22: Scenario B | E22: Scenario C | F22: Purpose
A23: Net income identity | B23: =IF(B16="","BUILD",IF(ABS(B16-(B14-B15))<='Tab 1 – Assumptions'!$B$12,"PASS","CHECK")) -> PASS | C23: =IF(C16="","BUILD",IF(ABS(C16-(C14-C15))<='Tab 1 – Assumptions'!$B$12,"PASS","CHECK")) -> BUILD | D23: =IF(D16="","BUILD",IF(ABS(D16-(D14-D15))<='Tab 1 – Assumptions'!$B$12,"PASS","CHECK")) -> BUILD | E23: =IF(E16="","BUILD",IF(ABS(E16-(E14-E15))<='Tab 1 – Assumptions'!$B$12,"PASS","CHECK")) -> BUILD | F23: Net income equals EBT less tax
A24: Interest consistency | B24: =IF(B13="","BUILD",IF(ABS(B13-(B11*'Tab 1 – Assumptions'!$B$10+B12*'Tab 1 – Assumptions'!$B$11))<='Tab 1 – Assumptions'!$B$12,"PASS","CHECK")) -> PASS | C24: =IF(C13="","BUILD",IF(ABS(C13-(C11*'Tab 1 – Assumptions'!$B$10+C12*'Tab 1 – Assumptions'!$B$11))<='Tab 1 – Assumptions'!$B$12,"PASS","CHECK")) -> BUILD | D24: =IF(D13="","BUILD",IF(ABS(D13-(D11*'Tab 1 – Assumptions'!$B$10+D12*'Tab 1 – Assumptions'!$B$11))<='Tab 1 – Assumptions'!$B$12,"PASS","CHECK")) -> BUILD | E24: =IF(E13="","BUILD",IF(ABS(E13-(E11*'Tab 1 – Assumptions'!$B$10+E12*'Tab 1 – Assumptions'!$B$11))<='Tab 1 – Assumptions'!$B$12,"PASS","CHECK")) -> BUILD | F24: Interest equals short- and long-term debt times stated rates
A25: EPS identity | B25: =IF(B18="","BUILD",IF(ABS(B18*B17-B16)<='Tab 1 – Assumptions'!$B$12,"PASS","CHECK")) -> PASS | C25: =IF(C18="","BUILD",IF(ABS(C18*C17-C16)<='Tab 1 – Assumptions'!$B$12,"PASS","CHECK")) -> BUILD | D25: =IF(D18="","BUILD",IF(ABS(D18*D17-D16)<='Tab 1 – Assumptions'!$B$12,"PASS","CHECK")) -> BUILD | E25: =IF(E18="","BUILD",IF(ABS(E18*E17-E16)<='Tab 1 – Assumptions'!$B$12,"PASS","CHECK")) -> BUILD | F25: EPS times shares equals net income

Sheet Tab 3 – Scenario Analysis
A1: APEX TECHNOLOGY CORPORATION — IPO SOURCES, USES & SCENARIO RECOMMENDATION
A2: Complete Parts A–D first to reconcile proceeds, debt, cash, assets, equity, and shares. Then complete Ratio Analysis. Return here to Part E to write your recommendation using the ratios.
A4: PART A — IPO SOURCES & USES
A5: Line item | B5: Scenario A | C5: Scenario B | D5: Scenario C | E5: Units | F5: Formula logic
A6: Gross proceeds | E6: $000s | F6: Offer price × new shares
A7: Less: issuance fees | E7: $000s | F7: Explicit assumption; no fees hidden
A8: Net proceeds available | E8: $000s | F8: Gross proceeds less fees
A9: Debt repayment | E9: $000s | F9: Link to scenario assumptions
A10: Growth capex / operating assets | E10: $000s | F10: Link to scenario assumptions
A11: Cash retained | E11: $000s | F11: Link to scenario assumptions
A12: Total uses | E12: $000s | F12: Debt repayment plus capex plus cash retained
A13: Sources less uses | E13: $000s | F13: Must equal zero
A15: PART B — POST-TRANSACTION BALANCE SHEET
A16: Line item | B16: Scenario A | C16: Scenario B | D16: Scenario C | E16: Units | F16: Formula logic
A17: Cash & equivalents | E17: $000s | F17: Pre cash + net proceeds − debt repayment − capex
A18: Accounts receivable | E18: $000s | F18: No closing adjustment in case
A19: Inventory | E19: $000s | F19: No closing adjustment in case
A20: Total current assets | E20: $000s | F20: Cash plus receivables plus inventory
A21: Property, plant & equipment | E21: $000s | F21: Pre PP&E plus growth capex / operating assets
A22: Intangibles & goodwill | E22: $000s | F22: No closing adjustment in case
A23: Total assets | E23: $000s | F23: Current assets plus PP&E plus intangibles
A24: Accounts payable | E24: $000s | F24: No closing adjustment in case
A25: Short-term debt | E25: $000s | F25: Link to scenario earnings debt schedule
A26: Long-term debt | E26: $000s | F26: Link to scenario earnings debt schedule
A27: Total liabilities | E27: $000s | F27: Accounts payable plus debt
A28: Common equity | E28: $000s | F28: Pre common equity plus net primary proceeds
A29: Total liabilities & equity | E29: $000s | F29: Total liabilities plus common equity
A31: PART C — CAPITAL STRUCTURE & PER-SHARE EFFECTS
A32: Metric | B32: Scenario A | C32: Scenario B | D32: Scenario C | E32: Units | F32: Formula logic
A33: Pre-money enterprise value | E33: $000s | F33: Link to FCFF valuation
A34: Post-money enterprise value | E34: $000s | F34: Pre EV plus capex × recognition assumption
A35: Post-IPO total debt | E35: $000s | F35: Short-term plus long-term debt
A36: Post-IPO cash | E36: $000s | F36: Link to post-transaction balance sheet
A37: Post-money equity value | E37: $000s | F37: Post EV less debt plus cash
A38: Post-IPO shares | E38: 000s shares | F38: Pre shares plus new shares
A39: Modeled post-money value / share | E39: $ / share | F39: Post-money equity value divided by post shares
A40: Earnings per share | E40: $ / share | F40: Scenario net income divided by post shares
A41: Book value per share | E41: $ / share | F41: Post common equity divided by post shares
A42: Prior-holder ownership | E42: % | F42: Pre shares divided by post shares
A43: Offer premium / (discount) to modeled post-money value | E43: % | F43: Offer price divided by modeled value less one
A45: PART D — TIE-OUT CHECKS
A46: Check | B46: Scenario A | C46: Scenario B | D46: Scenario C | E46: Tolerance | F46: What it proves
A47: Sources = uses | B47: =IF(B13="","BUILD",IF(ABS(B13)<='Tab 1 – Assumptions'!$B$12,"PASS","CHECK")) -> BUILD | C47: =IF(C13="","BUILD",IF(ABS(C13)<='Tab 1 – Assumptions'!$B$12,"PASS","CHECK")) -> BUILD | D47: =IF(D13="","BUILD",IF(ABS(D13)<='Tab 1 – Assumptions'!$B$12,"PASS","CHECK")) -> BUILD | E47: $000s | F47: Net proceeds are fully deployed or retained
A48: Debt roll-forward | B48: =IF(B35="","BUILD",IF(ABS('Tab 1 – Assumptions'!$B$40-B9-B35)<='Tab 1 – Assumptions'!$B$12,"PASS","CHECK")) -> BUILD | C48: =IF(C35="","BUILD",IF(ABS('Tab 1 – Assumptions'!$B$40-C9-C35)<='Tab 1 – Assumptions'!$B$12,"PASS","CHECK")) -> BUILD | D48: =IF(D35="","BUILD",IF(ABS('Tab 1 – Assumptions'!$B$40-D9-D35)<='Tab 1 – Assumptions'!$B$12,"PASS","CHECK")) -> BUILD | E48: $000s | F48: Pre debt less repayment equals post debt
A49: New equity | B49: =IF(B28="","BUILD",IF(ABS(B28-'Tab 1 – Assumptions'!$B$38-B8)<='Tab 1 – Assumptions'!$B$12,"PASS","CHECK")) -> BUILD | C49: =IF(C28="","BUILD",IF(ABS(C28-'Tab 1 – Assumptions'!$B$38-C8)<='Tab 1 – Assumptions'!$B$12,"PASS","CHECK")) -> BUILD | D49: =IF(D28="","BUILD",IF(ABS(D28-'Tab 1 – Assumptions'!$B$38-D8)<='Tab 1 – Assumptions'!$B$12,"PASS","CHECK")) -> BUILD | E49: $000s | F49: Post book equity equals pre equity plus net proceeds
A50: Balance sheet | B50: =IF(B23="","BUILD",IF(ABS(B23-B29)<='Tab 1 – Assumptions'!$B$12,"PASS","CHECK")) -> BUILD | C50: =IF(C23="","BUILD",IF(ABS(C23-C29)<='Tab 1 – Assumptions'!$B$12,"PASS","CHECK")) -> BUILD | D50: =IF(D23="","BUILD",IF(ABS(D23-D29)<='Tab 1 – Assumptions'!$B$12,"PASS","CHECK")) -> BUILD | E50: $000s | F50: Assets equal liabilities plus equity
A51: Share count | B51: =IF(B38="","BUILD",IF(ABS(B38-'Tab 1 – Assumptions'!$G$19-'Tab 1 – Assumptions'!$G$15)<='Tab 1 – Assumptions'!$B$12,"PASS","CHECK")) -> BUILD | C51: =IF(C38="","BUILD",IF(ABS(C38-'Tab 1 – Assumptions'!$G$19-'Tab 1 – Assumptions'!$G$15)<='Tab 1 – Assumptions'!$B$12,"PASS","CHECK")) -> BUILD | D51: =IF(D38="","BUILD",IF(ABS(D38-'Tab 1 – Assumptions'!$G$19-'Tab 1 – Assumptions'!$G$15)<='Tab 1 – Assumptions'!$B$12,"PASS","CHECK")) -> BUILD | E51: 000s shares | F51: Pre shares plus new shares equals post shares
A52: Post-money equity bridge | B52: =IF(B37="","BUILD",IF(ABS(B37-('Tab 2 – Valuation'!$F$14+B8))<='Tab 1 – Assumptions'!$B$12,"PASS","CHECK")) -> BUILD | C52: =IF(C37="","BUILD",IF(ABS(C37-('Tab 2 – Valuation'!$F$14+C8))<='Tab 1 – Assumptions'!$B$12,"PASS","CHECK")) -> BUILD | D52: =IF(D37="","BUILD",IF(ABS(D37-('Tab 2 – Valuation'!$F$14+D8))<='Tab 1 – Assumptions'!$B$12,"PASS","CHECK")) -> BUILD | E52: $000s | F52: Post-money equity equals pre-money equity plus net proceeds
A53: Per-share identity | B53: =IF(B39="","BUILD",IF(ABS(B39-B37/B38)<='Tab 1 – Assumptions'!$B$13,"PASS","CHECK")) -> BUILD | C53: =IF(C39="","BUILD",IF(ABS(C39-C37/C38)<='Tab 1 – Assumptions'!$B$13,"PASS","CHECK")) -> BUILD | D53: =IF(D39="","BUILD",IF(ABS(D39-D37/D38)<='Tab 1 – Assumptions'!$B$13,"PASS","CHECK")) -> BUILD | E53: $ / share | F53: Modeled value per share equals post-money equity value divided by post shares
A55: PART E — RETURN AFTER RATIO ANALYSIS: IPO RECOMMENDATION
A56: Offer-price recommendation | E56: State approve, reprice, or request evidence. Justify any proposed price or range with explicit scenarios.
A57: Proceeds deployment | E57: Choose Scenario A, B, or C; tie the choice to sources-and-uses and strategy.
A58: Valuation evidence | E58: Cite at least two models and explain why their results differ.
A59: Balance-sheet evidence | E59: Cite at least two reconciled debt, liquidity, or capital-structure outputs.
A60: Per-share / ratio evidence | E60: Cite EPS or value per share plus at least one audited ratio.
A61: Primary risk or limitation | E61: Identify the assumption most likely to change the decision.
A62: Monitoring trigger | E62: State a measurable item that would cause you to revisit price or deployment.

Sheet Tab 4 – Ratio Analysis
A1: APEX TECHNOLOGY CORPORATION — RATIO & PER-SHARE ANALYSIS
A2: Complete Scenario Analysis Parts A–D and Earnings first. Then calculate the pre-IPO baseline and scenario ratios. Return to Scenario Analysis Part E to write your recommendation using this evidence.
A4: AUDITED DEFINITIONS — BUILD EVERY VALUE WITH LINKED FORMULAS
A5: Metric | B5: Definition / denominator | C5: Pre-IPO | D5: Scenario A | E5: Scenario B | F5: Scenario C | G5: Interpretation / decision relevance
A6: Debt-to-equity | B6: Interest-bearing debt / common equity
A7: Current ratio | B7: Current assets / current liabilities
A8: Interest coverage | B8: EBIT / interest expense; N/M when interest is zero
A9: ROE (simplified) | B9: Net income / ending common equity
A10: Liabilities-to-assets | B10: Total liabilities / total assets
A11: ROA (simplified) | B11: Net income / ending total assets
A12: Net profit margin | B12: Net income / revenue
A13: Earnings per share | B13: Net income / diluted shares outstanding
A14: Book value per share | B14: Common equity / shares outstanding
A17: REFLECTION & AUDIT QUESTIONS
A18: Which scenario produces the strongest credit profile, and which linked ratios support that conclusion?
A19: Why can ROE and EPS decline after an IPO even when total net income rises?
A20: Which scenario has the strongest year-one EPS, and what long-run growth trade-off is not captured?
A21: Which ratio is most sensitive to the cash-retained assumption? Trace the numerator and denominator.
