Workbook

Sheet Tab 1 – Company Profile
B1: APEX TECHNOLOGY CORPORATION — COMPANY PROFILE
B2: BUS 311 Corporate Finance | Chapter 7: Equity Valuation & IPO Analysis | Pre-IPO Financial Data (Fiscal Year Ended Dec 31)
B4: INCOME STATEMENT ($ in thousands) | F4: KEY ASSUMPTIONS FOR THIS EXERCISE
B5: Line Item | C5: Amount ($000s) | D5: Notes | F5: Assumption | G5: Value | H5: Use In Model
B6: Revenue | C6: 850000 | D6: Software & services | F6: IPO Proceeds (Total) | G6: $400,000 | H6: Balance sheet cash injection
B7: Cost of Goods Sold | C7: 255000 | D7: 30% COGS margin | F7: Shares Issued in IPO | G7: 20,000,000 | H7: New shares at offering price
B8: Gross Profit | C8: =C6-C7 -> 595000 | F8: IPO Price Per Share | G8: $20.00 | H8: Calculated from valuation models
B9: Operating Expenses (SG&A + R&D) | C9: 340000 | D9: 40% of revenue | F9: Pre-IPO Shares Outstanding | G9: 50,000,000 | H9: Existing equity holders
B10: EBIT (Operating Income) | C10: =C8-C9 -> 255000 | D10: Earnings Before Interest & Taxes | F10: Post-IPO Total Shares | G10: 70,000,000 | H10: 50M + 20M new shares
B11: Interest Expense | C11: 36000 | D11: On $300M pre-IPO debt @ 12% | F11: Required Return on Equity (r) | G11: 10.5% | H11: DDM & Gordon Growth Model
B12: Earnings Before Tax (EBT) | C12: =C10-C11 -> 219000 | F12: Dividend Growth Rate (g) | G12: 4.0% | H12: Gordon Growth Model
B13: Income Tax (25%) | C13: =C12*0.25 -> 54750 | F13: Next Year Dividend (D₁) | G13: $0.84 | H13: DDM numerator
B14: Net Income | C14: =C12-C13 -> 164250 | F14: WACC (for FCF Model) | G14: 9.0% | H14: Weighted avg cost of capital
F15: FCF Growth Rate (long-run) | G15: 4.0% | H15: FCF perpetuity growth
B16: BALANCE SHEET ($ in thousands) — Pre-IPO | F16: Projected FCF (Year 1) | G16: $52,000 | H16: Free cash flow to firm ($000s)
B17: Balance Sheet Item | C17: Amount ($000s) | D17: Notes | F17: Net Debt (Pre-IPO) | G17: $255,000 | H17: LT Debt + ST Debt – Cash
B18: ASSETS | F18: IPO Proceeds to Debt Paydown (Scenario A) | G18: 50% | H18: Tab 4 Scenario Analysis
B19: Cash & Equivalents | C19: 45000 | F19: IPO Proceeds to Capex (Scenario B) | G19: 100% | H19: Tab 4 Scenario Analysis
B20: Accounts Receivable | C20: 120000
B21: Inventory | C21: 35000
B22: Total Current Assets | C22: =C19+C20+C21 -> 200000 | F22: COLOR CODE LEGEND
B23: Property, Plant & Equipment (Net) | C23: 280000 | F23: Blue text on yellow | H23: Student input cell — build your formula here
B24: Intangible Assets & Goodwill | C24: 150000 | F24: Black text on white | H24: Provided data or instructor formula
B25: Total Assets | C25: =C22+C23+C24 -> 630000 | F25: Bold black | H25: Subtotal or section total
B26: LIABILITIES & EQUITY
B27: Accounts Payable | C27: 85000
B28: Short-Term Debt | C28: 60000
B29: Total Current Liabilities | C29: =C27+C28 -> 145000
B30: Long-Term Debt | C30: 240000 | D30: $300M total debt
B31: Total Liabilities | C31: =C29+C30 -> 385000
B32: Shareholders' Equity | C32: 245000 | D32: Pre-IPO book value (Assets 630M – Liabilities 385M)
B33: Total Liabilities + Equity | C33: =C31+C32 -> 630000

Sheet Tab 2 – Equity Valuation
B1: APEX TECHNOLOGY CORPORATION — EQUITY VALUATION MODELS
B2: Tab 2 of 4 | Build the DDM and FCF models below. Yellow cells require your formula. Reference Tab 1 for inputs.
B4: PART A — DIVIDEND DISCOUNT MODEL (Gordon Growth) | F4: PART B — FREE CASH FLOW (FCF) MODEL
B5: Input Variable | C5: Symbol | D5: Value / Formula | F5: Input Variable | G5: Symbol | H5: Value / Formula
B6: Expected Dividend — D₁ (next year) | C6: D₁ | D6: $0.84 | F6: Projected FCF — Year 1 ($000s) | G6: FCF₁ | H6: $52,000
B7: Required Return on Equity — r | C7: r | D7: 10.5% | F7: WACC (Weighted Avg Cost of Capital) | G7: WACC | H7: 9.0%
B8: Constant Dividend Growth Rate — g | C8: g | D8: 4.0% | F8: Long-Run FCF Growth Rate | G8: g | H8: 4.0%
F9: Total Debt (Pre-IPO, $000s) | G9: Debt | H9: $300,000
B10: CALCULATION | F10: CALCULATION STEPS | G10: Cash
B11: Formula: | C11: P₀ = D₁ / (r – g) | D11: Hint: Use the values from rows 6–8 above | F11: Step 1 — Enterprise Value (EV) | G11: =H6/(H7-H8) -> 1040000 | H11: ← Hint: EV = FCF₁ / (WACC – g)
B12: DDM Stock Price (P₀) | C12: =D6/(D7-D8) -> 12.923077 | D12: ← Enter: =D6/(D7-D8) using row references | F12: Step 2 — Equity Value (K) | G12: =G11-H9+'Tab 1 – Company Profile'!C19 -> 785000 | H12: ← Hint: EV – Debt + Cash
F13: Step 3 — Price Per Share | G13: =G12*1000/('Tab 1 – Company Profile'!G10) -> 11.214286 | H13: ← Hint: Equity Value / Shares Outstanding Post IPO
B15: PART C — VALUATION SUMMARY & COMPARISON
B16: Model | C16: Estimated IPO Price | D16: Vs. Actual Offer ($20.00) | F16: Observation / Interpretation
B17: DDM (Gordon Growth Model) | C17: =C12 -> 12.923077 | D17: Reference your C12 result above | F17: Write 1 sentence: Is the DDM price above or below the IPO offer? What might explain the difference?
B18: FCF Model (Enterprise Value) | C18: =G13 -> 11.214286 | D18: Reference your G13 FCF price result | F18: Write 1 sentence: How does FCF price compare to DDM? Which model do you trust more for a tech firm?

Sheet Tab 2a-Net Income Calc
B2: Pre | C2: Scenario A | D2: Scenario B | E2: Scenario C/ Post
A3: Line Item | B3: Amount ($000s) | C3: Amount ($000s) | D3: Amount ($000s) | E3: Amount ($000s)
A4: Revenue | B4: 850000 | C4: 850000 | D4: 850000 | E4: 850000
A5: Cost of Goods Sold | B5: 255000 | C5: 255000 | D5: 255000 | E5: 255000
A6: Gross Profit | B6: =B4-B5 -> 595000 | C6: =C4-C5 -> 595000 | D6: =D4-D5 -> 595000 | E6: =E4-E5 -> 595000
A7: Operating Expenses (SG&A + R&D) | B7: 340000 | C7: 340000 | D7: 340000 | E7: 340000
A8: EBIT (Operating Income) | B8: =B6-B7 -> 255000 | C8: =C6-C7 -> 255000 | D8: =D6-D7 -> 255000 | E8: =E6-E7 -> 255000
A9: Interest Expense | B9: 36000 | C9: 0 | D9: 36000 | E9: 12000
A10: Earnings Before Tax (EBT) | B10: =B8-B9 -> 219000 | C10: =C8-C9 -> 255000 | D10: =D8-D9 -> 219000 | E10: =E8-E9 -> 243000
A11: Income Tax (25%) | B11: =B10*0.25 -> 54750 | C11: =C10*0.25 -> 63750 | D11: =D10*0.25 -> 54750 | E11: =E10*0.25 -> 60750
A12: Net Income | B12: =B10-B11 -> 164250 | C12: =C10-C11 -> 191250 | D12: =D10-D11 -> 164250 | E12: =E10-E11 -> 182250
A14: ROE | C14: =C12/645000 -> 0.29651163 | D14: =D12/645000 -> 0.25465116 | E14: =E12/645000 -> 0.28255814

Sheet Tab 3 – Ratio Analysis
B1: APEX TECHNOLOGY CORPORATION — RATIO ANALYSIS
B2: Tab 3 of 4 | Calculate each ratio BEFORE and AFTER the $400M IPO. Build formulas in yellow cells — do not hardcode numbers.
B4: POST-IPO BALANCE SHEET ADJUSTMENTS (Scenario: 50% Debt Paydown / 50% Capex)
B5: Balance Sheet Item | C5: Formula / Logic | D5: Pre-IPO ($000s) | E5: IPO Impact ($000s) | F5: Post-IPO ($000s) | G5: Notes
B6: Cash & Equivalents | C6: No Change in Cash $200M to Debt; $200mm to PPE | D6: 45000 | E6: 0 | F6: =D6+E6 -> 45000
B7: Short-Term Debt | C7: –$60M paydown (part of 50% debt repayment) | D7: 60000 | E7: -60000 | F7: =D7+E7 -> 0 | G7: Paid off with IPO proceeds
B8: Long-Term Debt | C8: –$140M paydown ($200M total debt paid) | D8: 240000 | E8: -140000 | F8: =D8+E8 -> 100000 | G8: $300M total – $160M remaining
B9: PP&E (Net) | C9: +$200M capex deployed | D9: 280000 | E9: +200,000 | F9: =D9+E9 -> 480000 | G9: 50% of IPO to new equipment
B10: Shareholders' Equity | C10: +$400M IPO proceeds (new equity) | D10: 245000 | E10: +400,000 | F10: =D10+E10 -> 645000 | G10: New equity raised from public
B11: Interest Expense | C11: On $300M pre-IPO debt @ 12%; $100M total Debt at 12% | D11: ='Tab 1 – Company Profile'!C11 -> 36000 | E11: -24000 | F11: =D11+E11 -> 12000
B12: Net Income | C12: NI inc by $18,000 after tax ($24*(1-tax rate) | D12: 164250 | E12: 18000 | F12: =D12+E12 -> 182250
B14: KEY FINANCIAL RATIOS — BEFORE vs. AFTER IPO
B15: Ratio | C15: Formula | D15: Pre-IPO Value | E15: Post-IPO Value ▶ BUILD | F15: Change | G15: Direction | H15: Interpretation (1 sentence)
B16: Debt-to-Equity Ratio | C16: Total Debt / Shareholders' Equity | D16: =(D7+D8)/D10 -> 1.2244898 | E16: =(F7+F8)/F10 -> 0.15503876 | F16: =E16-D16 -> -1.069451 | G16: ↓ Improved | H16: Leverage ↓ when equity rises
B17: Current Ratio | C17: Current Assets / Current Liabilities | D17: =(45000+120000+35000)/(60000+85000) -> 1.3793103 | E17: =('Tab 1 – Company Profile'!C22)/('Tab 1 – Company Profile'!C29+E7) -> 2.3529412 | F17: =E17-D17 -> 0.97363083 | G17: ↑ Improved | H17: Liquidity ↑ as cash increases
B18: Interest Coverage | C18: EBIT / Interest Expense | D18: ='Tab 1 – Company Profile'!C10/'Tab 1 – Company Profile'!C11 -> 7.0833333 | E18: ='Tab 1 – Company Profile'!C10/(F11) -> 21.25 | F18: =E18-D18 -> 14.166667 | G18: ↑ Improved | H18: Coverage ↑ if debt & interest drop
B19: Return on Equity (ROE) | C19: Net Income / Shareholders' Equity | D19: =164500/245000 -> 0.67142857 | E19: ='Tab 1 – Company Profile'!C14/'Tab 3 – Ratio Analysis'!F10 -> 0.25465116 | F19: =E19-D19 -> -0.41677741 | G19: ↓ Declines | H19: ROE diluted by new equity
B20: Debt Ratio | C20: Total Liabilities / Total Assets | D20: ='Tab 1 – Company Profile'!C31/'Tab 1 – Company Profile'!C25 -> 0.61111111 | E20: =('Tab 1 – Company Profile'!C31-200000)/('Tab 1 – Company Profile'!C25+200000) -> 0.22289157 | F20: =E20-D20 -> -0.38821954 | G20: ↓ Improved | H20: Debt share of assets decreases
B21: Return on Assets (ROA) | C21: Net Income / Total Assets | D21: ='Tab 1 – Company Profile'!C14/(45000+120000+35000+280000+150000) -> 0.26071429 | E21: =F12/('Tab 1 – Company Profile'!C25+200000) -> 0.21957831 | F21: =E21-D21 -> -0.041135972 | G21: ↔ Mixed | H21: ROA changes with asset base
B22: Net Profit Margin | C22: Net Income / Revenue | D22: ='Tab 1 – Company Profile'!C14/'Tab 1 – Company Profile'!C6 -> 0.19323529 | E22: =F12/'Tab 1 – Company Profile'!C6 -> 0.21441176 | F22: =E22-D22 -> 0.021176471 | G22: ↑ Improved | H22: NI ↑ if debt & interest drop
B24: REFLECTION QUESTIONS
B25: Q1: Which ratio showed the MOST improvement after the IPO? Why does that make sense given how proceeds were used? | E25: [Type your answer here]
B26: Q2: Why does ROE decline even though net income stays the same? Is this bad for shareholders? | E26: [Type your answer here]
B27: Q3: A credit rating agency reviews Apex after the IPO. Which two ratios would they focus on most, and why? | E27: [Type your answer here]

Sheet Tab 4 – Scenario Analysis
B1: APEX TECHNOLOGY CORPORATION — SCENARIO ANALYSIS: USES OF IPO PROCEEDS
B2: Tab 4 of 4 | Apex raised $400M in its IPO. Analyze three different strategies for deploying the proceeds and their ratio impact.- Scnario C already done on Ratio Analysis Page
B4: THREE SCENARIOS — $400M IPO PROCEEDS DEPLOYMENT
B5: Metric / Ratio | C5: SCENARIO A | D5: SCENARIO B | E5: SCENARIO C
C6: Debt Paydown (100% to debt retirement) | D6: Capital Investment (100% to new equipment/R&D) | E6: Balanced Mix (50% debt / 50% capex)
B7: Debt Retired ($000s) | C7: $400,000 | D7: $0 | E7: 200000
B8: New Capex / Assets Added ($000s) | C8: $0 | D8: $400,000 | E8: 200000
B9: Total Debt Post-IPO ($000s) | C9: $0 | D9: $300,000 | E9: 100000
B10: Annual Interest Saved ($000s) | C10: $36,000 | D10: $0 | E10: $18,000
B11: New Asset Base Addition ($000s) | C11: $0 | D11: $400,000 | E11: $200,000
B12: Net Income | C12: 191250 | D12: 164250 | E12: 182250
B14: RATIO IMPACT BY SCENARIO — STUDENT BUILDS ALL YELLOW CELLS
B15: Ratio | C15: Pre-IPO (Baseline) | D15: Scenario A: Debt Paydown | E15: Scenario B: Full Capex | F15: Scenario C: Balanced Mix
B16: Debt-to-Equity Ratio | C16: 1.22x | D16: 0.00x | E16: 0.47x | F16: ='Tab 3 – Ratio Analysis'!E16 -> 0.15503876 | G16: Total Debt / Shareholders' Equity
B17: Current Ratio | C17: 1.38x | D17: 2.07x | E17: 1.38x | F17: ='Tab 3 – Ratio Analysis'!E17 -> 2.3529412 | G17: Current Assets / Current Liabilities
B18: Interest Coverage (EBIT/Int) | C18: 7.08x | D18: N/A (no debt) | E18: 7.08x | F18: ='Tab 3 – Ratio Analysis'!E18 -> 21.25 | G18: EBIT / Interest Expense
B19: Return on Equity (ROE) | C19: 0.67 | D19: =C12/645000 -> 0.29651163 | E19: =D12/645000 -> 0.25465116 | F19: =E12/645000 -> 0.28255814 | G19: Net Income / Shareholders' Equity
B20: Debt Ratio (Debt/Assets) | C20: 61.1% | D20: 11.6% | E20: 37.4% | F20: ='Tab 3 – Ratio Analysis'!E20 -> 0.22289157 | G20: Total Liabilities / Total Assets
B21: Net Profit Margin | C21: 19.3% | D21: 22.5% | E21: 19.3% | F21: ='Tab 3 – Ratio Analysis'!E22 -> 0.21441176 | G21: Net Income / Total Assets
B22: HINT: For Scenario A (all debt paydown): Post-IPO Debt = $0, Post-IPO Equity = $645M, Interest Expense = $0. Recalculate each ratio using the new inputs.
B24: ANALYSIS — WHICH SCENARIO IS BEST?
B25: Evaluation Criteria | C25: Best Scenario? | D25: Your Reasoning (1 sentence)
B26: Best for Short-Term Liquidity | C26: A / B / C | D26: [Write your reasoning here]
B27: Best for Long-Term Growth | C27: A / B / C | D27: [Write your reasoning here]
B28: Best for Credit Rating | C28: A / B / C | D28: [Write your reasoning here]
B29: Best for EPS (Earnings per Share) | C29: A / B / C | D29: [Write your reasoning here]
B30: Best Overall Strategic Fit for a Tech Company | C30: A / B / C | D30: [Write your reasoning here]

Sheet 🔑 Answer Key
B1: 🔑 APEX ANSWER KEY
B2: Apex Technology Corp. IPO Valuation & Ratio Analysis — Complete Solution
B4: TAB 2 — EQUITY VALUATION ANSWERS
B5: Item | C5: Answer | D5: Formula Used | E5: Notes for Discussion
B6: DDM Stock Price (P₀) | C6: 12.92 | D6: Formula: D₁/(r–g) = $0.84/(10.5%–4.0%) | E6: Below IPO price — DDM is sensitive to dividend size. Apex pays modest dividends for a tech firm.
B7: FCF — Enterprise Value | C7: $1,040,000K | D7: Formula: FCF₁/(WACC–g) = $52,000/(9%–4%) | E7: EV = $1.04 billion. Large tech companies often trade at high EV multiples.
B8: FCF — Equity Value | C8: $785,000K | D8: Formula: EV – Net Debt = $1,040,000 – $255,000 | E8: Net debt pre-IPO = $300M debt – $45M cash = $255M
B9: FCF — Price Per Share | C9: $11.21 | D9: Formula: $785,000,000 / 70,000,000 shares | E9: Below the $20 offer — suggests IPO was priced at premium to intrinsic value
B10: Observation | C10: Both models below $20 | D10: Market pricing includes growth premium | E10: Real IPOs price based on comps and growth outlook — not just DCF. Underwriting pressure to price attractively.
B12: TAB 3 — RATIO ANALYSIS ANSWERS (50/50 Scenario)
B13: Ratio | C13: Pre-IPO | D13: Post-IPO | E13: Change | F13: What's happening? | H13: Formula
B14: Debt-to-Equity | C14: 1.22x | D14: 0.16x | E14: ='Tab 3 – Ratio Analysis'!F16 -> -1.069451 | F14: Leverage drops sharply. $300M→$100M debt; equity $245M→$645M | H14: Total Debt / Shareholders' Equity
B15: Current Ratio | C15: 1.38x | D15: ='Tab 3 – Ratio Analysis'!E17 -> 2.3529412 | E15: ='Tab 3 – Ratio Analysis'!F17 -> 0.97363083 | F15: Cash from capex half stays temporarily; current liabilities drop | H15: Current Assets / Current Liabilities
B16: Interest Coverage | C16: 7.36x | D16: ='Tab 3 – Ratio Analysis'!E18 -> 21.25 | E16: ='Tab 3 – Ratio Analysis'!F18 -> 14.166667 | F16: EBIT unchanged; interest drops from $36K to $18K after paydown | H16: EBIT / Interest Expense
B17: Return on Equity | C17: 0.6714 | D17: ='Tab 3 – Ratio Analysis'!E19 -> 0.25465116 | E17: ='Tab 3 – Ratio Analysis'!F19 -> -0.41677741 | F17: Net income same; equity base now $645M vs $245M — dilution is dramatic | H17: Net Income / Shareholders' Equity
B18: Debt Ratio | C18: 0.6111 | D18: ='Tab 3 – Ratio Analysis'!E20 -> 0.22289157 | E18: ='Tab 3 – Ratio Analysis'!F20 -> -0.38821954 | F18: Massive improvement in solvency — assets grow, debt shrinks | H18: Total Liabilities / Total Assets
B19: ROA | C19: 0.26x | D19: ='Tab 3 – Ratio Analysis'!E21 -> 0.21957831 | E19: ='Tab 3 – Ratio Analysis'!F21 -> -0.041135972 | F19: Asset base grows $200M but income unchanged — dilution to assets | H19: Net Income / Total Assets
B20: Net Profit Margin | C20: 0.19323529 | D20: ='Tab 3 – Ratio Analysis'!E22 -> 0.21441176 | E20: ='Tab 3 – Ratio Analysis'!F22 -> 0.021176471 | F20: NI ↑ if debt & interest drop | H20: Net Income / Revenue
B21: TAB 4 — SCENARIO ANALYSIS ANSWERS
B22: Ratio | C22: Pre-IPO | D22: Scenario A (All Debt) | E22: Scenario B (All Capex) | F22: Scenario C (Balanced)
B23: Debt-to-Equity | C23: =C14 -> 1.22x | D23: ='Tab 4 – Scenario Analysis'!D16 -> 0.00x | E23: ='Tab 4 – Scenario Analysis'!E16 -> 0.47x | F23: =D14 -> 0.16x
B24: Current Ratio | C24: =C15 -> 1.38x | D24: ='Tab 4 – Scenario Analysis'!D17 -> 2.07x | E24: ='Tab 4 – Scenario Analysis'!E17 -> 1.38x | F24: =D15 -> 2.3529412
B25: Interest Coverage | C25: =C16 -> 7.36x | D25: ='Tab 4 – Scenario Analysis'!D18 -> N/A (no debt) | E25: ='Tab 4 – Scenario Analysis'!E18 -> 7.08x | F25: =D16 -> 21.25
B26: ROE | C26: =C17 -> 0.6714 | D26: ='Tab 4 – Scenario Analysis'!D19 -> 0.29651163 | E26: ='Tab 4 – Scenario Analysis'!E19 -> 0.25465116 | F26: =D17 -> 0.25465116
B27: Debt Ratio | C27: =C18 -> 0.6111 | D27: ='Tab 4 – Scenario Analysis'!D20 -> 11.6% | E27: ='Tab 4 – Scenario Analysis'!E20 -> 37.4% | F27: =D18 -> 0.22289157
B28: Net Profit Margin | C28: =C20 -> 0.19323529 | D28: ='Tab 4 – Scenario Analysis'!D21 -> 22.5% | E28: ='Tab 4 – Scenario Analysis'!E21 -> 19.3% | F28: =D20 -> 0.21441176
B29: *Scenario A: All $300M debt retired → interest expense = $0. Net Income rises by $27M (after-tax interest saving: $36M × 0.75 = $27M). Net margin improves from 13.5% to 17.6%.
B30: TAB 4 — BEST SCENARIO ANSWERS
B31: Evaluation Criteria | C31: Best Scenario | D31: Instructor Notes
B32: Best for Short-Term Liquidity | C32: A | D32: All debt retired; no debt service; cash remains strong
B33: Best for Long-Term Growth | C33: B | D33: Full capex investment builds asset base for future revenue growth
B34: Best for Credit Rating | C34: A | D34: Debt-to-equity drops to 0; coverage ratio dramatically improves
B35: Best for EPS | C35: A | D35: Eliminating interest saves $27M after-tax, directly boosting EPS
B36: Best Strategic Fit — Tech Company | C36: C or B | D36: Tech firms need capex/R&D; some leverage reduction + reinvestment balances growth vs. risk
