Workbook

Sheet Cover
B2: BUS 311 — Corporate Finance
B3: Chapter 8: Net Present Value & Capital Budgeting
B4: VeridianEnergy Corp — Capital Budgeting Decision Analysis
B6: Student Name: | C6: Date: | D6: Section:
B9: ASSIGNMENT OVERVIEW
B10: Company: | C10: VeridianEnergy Corp is an independent power producer evaluating three competing renewable energy projects. Only capital and strategic constraints limit which projects can be pursued.
B11: Your Role: | C11: You are the lead financial analyst. Management has asked you to evaluate each project using NPV, IRR, and Profitability Index, then deliver a final investment recommendation.
B12: Capital Budget: | C12: VeridianEnergy has a maximum capital budget of $18,000,000 for this investment cycle.
B13: Discount Rate: | C13: The company's weighted average cost of capital (WACC) is 9.0%.
B15: WORKSHEET GUIDE
B16: Tab 1 → Cover | C16: This page: assignment overview and instructions
B17: Tab 2 → Project Data | C17: Review the three project cash flow assumptions
B18: Tab 3 → NPV Analysis | C18: Calculate NPV for each project using the NPV formula
B19: Tab 4 → IRR & PI Analysis | C19: Compute IRR and Profitability Index; rank projects
B20: Tab 5 → Recommendation | C20: Draft your final investment memo to management
B21: Tab 6 → Answer Key | C21: INSTRUCTOR ONLY — Full worked solutions
B23: COLOR CODING GUIDE
B24: Sample | C24: Yellow cells — Enter your answers here
B25: Sample | C25: Blue text — Hardcoded input values (given data)
B26: Sample | C26: Green text — Formulas linking to other tabs
B27: Sample | C27: Black text — Formulas you must build

Sheet Project Data
B2: VeridianEnergy Corp — Project Cash Flow Data
B3: All figures in USD. WACC = 9.0% | Capital Budget = $18,000,000
C5: Project A: Solar Farm | D5: Project B: Wind Turbines | E5: Project C: Hydro Plant
C6: Nevada Desert | D6: Texas Coast | E6: Pacific Northwest
B7: Initial Investment (Year 0) | C7: -12000000 | D7: -8000000 | E7: -18000000
B8: Year 1 Cash Flow | C8: 2200000 | D8: 1800000 | E8: 3500000
B9: Year 2 Cash Flow | C9: 2400000 | D9: 2000000 | E9: 3800000
B10: Year 3 Cash Flow | C10: 2600000 | D10: 2200000 | E10: 4100000
B11: Year 4 Cash Flow | C11: 2800000 | D11: 2400000 | E11: 4400000
B12: Year 5 Cash Flow | C12: 3000000 | D12: 2600000 | E12: 4700000
B13: Year 6 Cash Flow | C13: 3200000 | D13: 2800000 | E13: 5000000
B14: Year 7 Cash Flow | C14: 3400000 | D14: =3000000+D19 -> 3200000 | E14: 5300000
B15: Year 8 Cash Flow | C15: 3600000 | D15: N/A | E15: 5600000
B16: Year 9 Cash Flow | C16: 3800000 | D16: N/A | E16: 5900000
B17: Year 10 Cash Flow** | C17: =4000000+C19 -> 4500000 | D17: N/A | E17: =6200000+E19 -> 7000000
B18: Project Life (Years) | C18: 10 | D18: 7 | E18: 10
B19: Salvage Value (Year N) | C19: 500000 | D19: 200000 | E19: 800000
B21: Notes: Cash flows represent net operating cash flows after tax. Salvage value is received at end of project life and should be added to final year cash flow in your analysis.

Sheet NPV Analysis
B2: Tab 3: NPV Analysis — VeridianEnergy Corp
B3: Instructions: For each project, calculate the NPV using the NPV function. Cash flows from Year 1 onward go into the NPV function; the Year 0 investment is added separately. Remember: the salvage value should be added to the final year cash flow before calculating NPV. Yellow cells require your input or formula.
C7: Project A Solar Farm | D7: Project B Wind Turbines | E7: Project C Hydro Plant
B8: Discount Rate (WACC) | C8: 9.0% | D8: 9.0% | E8: 9.0%
B9: Initial Investment (Year 0) | C9: ='Project Data'!C7 -> -12000000 | D9: ='Project Data'!D7 -> -8000000 | E9: ='Project Data'!E7 -> -18000000
B10: Project Life (Years) | C10: ='Project Data'!C18 -> 10 | D10: ='Project Data'!D18 -> 7 | E10: ='Project Data'!E18 -> 10
B12: STEP 1 — Enter Final Year Cash Flow (Operating CF + Salvage Value)
B13: Final Year Operating CF | C13: ='Project Data'!C17 -> 4500000 | D13: ='Project Data'!D14 -> 3200000 | E13: ='Project Data'!E17 -> 7000000
B14: Salvage Value | C14: ='Project Data'!C19 -> 500000 | D14: ='Project Data'!D19 -> 200000 | E14: ='Project Data'!E19 -> 800000
B15: Total Final Year CF (incl. Salvage) | C15: =C13+C14 -> 5000000 | D15: =D13+D14 -> 3400000 | E15: =E13+E14 -> 7800000
B17: STEP 2 — Calculate Net Present Value | Formula: =NPV(rate, CF1:CFn) + C0
B18: Hint: =NPV($C$8, [Year1_CF, Year2_CF, ..., FinalYearCF_with_Salvage]) + [Year0_Investment]
B19: NET PRESENT VALUE | C19: =NPV(C8,'Project Data'!C8:C17)+'NPV Analysis'!C9 -> 7204607.1 | D19: =NPV(D8,'Project Data'!D8:D14)+'NPV Analysis'!D9 -> 3843640 | E19: =NPV(E8,'Project Data'!E8:E17)+'NPV Analysis'!E9 -> 12111563
C20: =_xlfn.FORMULATEXT(C19) -> =NPV(C8,'Project Data'!C8:C17)+'NPV Analysis'!C9 | D20: =_xlfn.FORMULATEXT(D19) -> =NPV(D8,'Project Data'!D8:D14)+'NPV Analysis'!D9 | E20: =_xlfn.FORMULATEXT(E19) -> =NPV(E8,'Project Data'!E8:E17)+'NPV Analysis'!E9
B21: STEP 3 — Apply the NPV Rule
B22: Accept / Reject? | C22: Accept | D22: Accept | E22: Accept
B23: Justification (brief) | C23: NPV >0 | D23: NPV >0 | E23: NPV >0

Sheet IRR & PI Analysis
B2: Tab 4: IRR & Profitability Index Analysis
B3: Instructions: (1) Compute IRR using Excel's =IRR() function with all cash flows including Year 0. (2) Compute the Profitability Index = PV of Future CFs ÷ |Initial Investment|. (3) Complete the ranking table and answer the capital rationing question at the bottom.
C7: Project A Solar Farm | D7: Project B Wind Turbines | E7: Project C Hydro Plant
B8: PART A — Internal Rate of Return (IRR) | Formula: =IRR(CF0:CFn)
B9: Hint: Include ALL cash flows (Year 0 through final year with salvage) as a contiguous range in =IRR()
B10: INTERNAL RATE OF RETURN | C10: =IRR('Project Data'!C7:C17) -> 0.19742659 | D10: =IRR('Project Data'!D7:D14) -> 0.20799876 | E10: =IRR('Project Data'!E7:E17) -> 0.20964699
B11: WACC (Hurdle Rate) | C11: 0.09 | D11: 0.09 | E11: 0.09
B12: Accept? (IRR > WACC?) | C12: Accept | D12: Accept | E12: Accept
B14: PART B — Profitability Index | Formula: PI = PV of Future CFs ÷ |Initial Investment|
B15: Hint: PV of Future CFs = NPV (from Tab 3) + |Initial Investment|. Then PI = PV of Future CFs ÷ |Initial Investment|
B16: PV of Future Cash Flows | C16: ='NPV Analysis'!C19+ABS('NPV Analysis'!C9) -> 19204607 | D16: ='NPV Analysis'!D19+ABS('NPV Analysis'!D9) -> 11843640 | E16: ='NPV Analysis'!E19+ABS('NPV Analysis'!E9) -> 30111563
B17: Initial Investment (absolute value) | C17: {=ABS('Project Data'!C7:E7)} -> 12000000 | D17: 8000000 | E17: 18000000
B18: PROFITABILITY INDEX | C18: =C16/C17 -> 1.6003839 | D18: =D16/D17 -> 1.480455 | E18: =E16/E17 -> 1.6728646
B19: Rank (1 = Highest PI) | C19: 2 | D19: 3 | E19: 1
B21: PART C — Capital Rationing Decision | Budget = $18,000,000
B22: Which project(s) can be funded within the $18M budget if you must choose using the PI ranking?
B24: What is the total NPV of your selected project(s)?
B26: Would your answer change if you used IRR ranking instead? Why or why not?

Sheet Recommendation
B2: Tab 5: Investment Recommendation Memo
B3: Imagine you are presenting to VeridianEnergy's CFO. Write your recommendation in the yellow cells below.
B5: To: | C5: VeridianEnergy Corp — Chief Financial Officer
B6: From:
B7: Date:
B8: Re: | C8: Chapter 8 Capital Budgeting Analysis — Project Recommendation
B10: Executive Summary (3–5 sentences): | C10: Summarize your findings. Which project(s) do you recommend? What was the basis?
B15: NPV Analysis Summary (cite your numbers): | C15: State the NPV for each project and what it means for shareholder value.
B20: IRR Analysis Summary (compare to WACC): | C20: State each project's IRR. Does it clear the 9% hurdle? Is there a conflict with NPV ranking?
B25: Profitability Index & Capital Rationing: | C25: If budget is $18M, which project(s) maximize value? Reference your PI scores.
B30: Recommendation & Rationale: | C30: Final recommendation with one paragraph of supporting logic.
B35: Key Risks to Monitor: | C35: List 2–3 risks that could change your recommendation.

Sheet Answer Key
B2: ⚠ INSTRUCTOR ANSWER KEY — NOT FOR STUDENT DISTRIBUTION ⚠
B3: All answers calculated with WACC = 9.0%. Cash flows use operating CFs + salvage in final year.
B5: PROJECT SUMMARY
C6: Project A — Solar Farm | D6: Project B — Wind Turbines | E6: Project C — Hydro Plant
B7: Initial Investment | C7: -12000000 | D7: -8000000 | E7: -18000000
B8: Project Life (Years) | C8: 10 | D8: 7 | E8: 10
B10: NPV ANALYSIS
B11: Total Final Year CF (incl. Salvage) | C11: 4500000 | D11: 3200000 | E11: 7000000
B12: NET PRESENT VALUE | C12: 7204607.1 | D12: 3843640 | E12: 12111563
B13: Accept / Reject (NPV > 0?) | C13: ACCEPT ✓ | D13: ACCEPT ✓ | E13: ACCEPT ✓
B15: IRR ANALYSIS
B16: INTERNAL RATE OF RETURN | C16: 0.19742659 | D16: 0.20799876 | E16: 0.20964699
B17: WACC (Hurdle Rate) | C17: 0.09 | D17: 0.09 | E17: 0.09
B18: Exceeds Hurdle Rate? | C18: YES | D18: YES | E18: YES
B20: PROFITABILITY INDEX
B21: PV of Future Cash Flows | C21: 19204607 | D21: 11843640 | E21: 30111563
B22: Initial Investment (absolute value) | C22: 12000000 | D22: 8000000 | E22: 18000000
B23: PROFITABILITY INDEX | C23: 1.6003839 | D23: 1.480455 | E23: 1.6728646
B24: PI Rank (1=Best) | C24: 2 | D24: 3 | E24: 1
B26: CAPITAL RATIONING — Budget = $18,000,000
B27: PI Ranking | C27: 1st: Project C (PI=1.67, Cost=$18M) | 2nd: Project A (PI=1.60, Cost=$12M) | 3rd: Project B (PI=1.48, Cost=$8M)
B28: Optimal Selection | C28: Project C ($18M) fits exactly within the $18M budget → BEST CHOICE under PI ranking. Project A ($12M) + Project B ($8M) = $20M → EXCEEDS BUDGET — cannot fund both. Fund Project C alone: NPV = $12,111,563. This maximizes value per dollar AND total NPV within the constraint.
B29: Best Single Project by PI | C29: Project C has highest PI = 1.67x — best value per dollar invested. It also happens to fit the $18M budget exactly. Note: Project C also has the highest absolute NPV ($12,111,563), so PI and NPV rankings agree here.
B30: Key Teaching Point | C30: With an $18M budget: Fund Project C ($18M, PI=1.67, highest PI). It fits exactly within the budget and generates the highest NPV ($12,111,563). A+B together would exceed the budget ($20M total). This is a case where PI ranking, budget feasibility, and NPV maximization all point to the same decision — Project C.
B32: QUICK REFERENCE SUMMARY
B33: Metric | C33: Project A | D33: Project B | E33: Project C
B34: NPV | C34: $7,204,607 | D34: $3,843,640 | E34: $12,111,563
B35: IRR | C35: 19.7% | D35: 20.8% | E35: 21.0%
B36: PI | C36: 1.60x | D36: 1.48x | E36: 1.67x
B37: PI Rank | C37: #2 | D37: #3 | E37: #1
B38: Decision (standalone) | C38: ACCEPT | D38: ACCEPT | E38: ACCEPT
