Workbook

Sheet Chapter 8
D12: Chapter 8
D14: Problems 1-35
D18: Input boxes in tan
D19: Output boxes in yellow
D20: Given data in blue
D21: Calculations in red
D22: Answers in green
D24: NOTE: Some functions used in these spreadsheets may require that
D25: the "Analysis ToolPak" or "Solver Add-In" be installed in Excel.
D26: To install these, click on the File tab
D27: then "Options," "Add-Ins" and select
D28: "Go." Check "Analyis ToolPak" and
D29: "Solver Add-In," then click "OK."

Sheet #1
C1: Chapter 8
C2: Question 1
C4: Input area: | N4: Input area:
C7: Dividend paid | D7: 3.65 | N7: Dividend paid | O7: 1.9
C8: Dividend growth rate | D8: 0.04 | N8: Dividend growth rate | O8: 0.06
C9: Required return | D9: 0.105 | N9: Required return | O9: 0.1
C10: Year for price | D10: 0 | N10: Year for price | O10: 0
C11: Year for price | D11: 3 | N11: Year for price | O11: 3
C12: Year for price | D12: 15 | N12: Year for price | O12: 5
C15: Output area: | N15: Output area:
C18: ="Price in "&D10&" years" -> Price in 0 years | D18: =(D7*(1+D8)^(D10+1))/(D9-D8) -> 58.4 | G18: =_xlfn.FORMULATEXT(D18) -> =(D7*(1+D8)^(D10+1))/(D9-D8) | N18: ="Price in "&O10&" years" -> Price in 0 years | O18: =(O7*(1+O8)^(O10+1))/(O9-O8) -> 50.35 | R18: =_xlfn.FORMULATEXT(O18) -> =(O7*(1+O8)^(O10+1))/(O9-O8)
C19: ="Price in "&D11&" years" -> Price in 3 years | D19: =(D7*(1+D8)^(D11+1))/(D9-D8) -> 65.692058 | G19: =_xlfn.FORMULATEXT(D19) -> =(D7*(1+D8)^(D11+1))/(D9-D8) | N19: ="Price in "&O11&" years" -> Price in 3 years | O19: =(O7*(1+O8)^(O11+1))/(O9-O8) -> 59.967656 | R19: =_xlfn.FORMULATEXT(O19) -> =(O7*(1+O8)^(O11+1))/(O9-O8)
C20: ="Price in "&D12&" years" -> Price in 15 years | D20: =(D7*(1+D8)^(D12+1))/(D9-D8) -> 105.1751 | G20: =_xlfn.FORMULATEXT(D20) -> =(D7*(1+D8)^(D12+1))/(D9-D8) | N20: ="Price in "&O12&" years" -> Price in 5 years | O20: =(O7*(1+O8)^(O12+1))/(O9-O8) -> 67.379658 | R20: =_xlfn.FORMULATEXT(O20) -> =(O7*(1+O8)^(O12+1))/(O9-O8)

Sheet #2
C1: Chapter 8
C2: Question 2
C4: Input area:
C7: Dividend paid | D7: 1.93
C8: Dividend growth rate | D8: 0.043
C9: Stock price | D9: 41
C12: Output area:
C15: Required return | D15: =D7/D9+D8 -> 0.090073171

Sheet #3
C1: Chapter 8
C2: Question 3
C4: Input area:
C7: Dividend paid | D7: ='#2'!D7 -> 1.93
C8: Dividend growth rate | D8: ='#2'!D8 -> 0.043
C9: Share price | D9: ='#2'!D9 -> 41
C12: Output area:
C15: Dividend yield | D15: =D7/D9 -> 0.047073171
C17: Capital gains yield | D17: =D8 -> 0.043

Sheet #4
C1: Chapter 8
C2: Question 4
C4: Input area:
C7: Dividend next year | D7: 3.26
C8: Dividend growth rate | D8: 0.0375
C9: Required return | D9: 0.11
C12: Output area:
C15: Price | D15: =D7/(D9-D8) -> 44.965517

Sheet #5
C1: Chapter 8
C2: Question 5
C4: Input area:
C7: Dividend growth rate | D7: 0.032
C8: Dividend yield | D8: 0.056
C11: Output area:
C14: Required return | D14: =D7+D8 -> 0.088

Sheet #6
C1: Chapter 8
C2: Question 6
C4: Input area:
C7: Stock price | D7: 87
C8: Required return | D8: 0.105
C11: Output area:
C14: Dividend yield | D14: =D8/2 -> 0.0525
C16: Next year's dividend | D16: =D14*D7 -> 4.5675
C18: Current dividend | D18: =D16/(1+D14) -> 4.3396675

Sheet #7
C1: Chapter 8
C2: Question 7
C4: Input area:
C7: Current dividend | D7: 8.5
C8: Years until dividend ceases | D8: 13
C9: Required return | D9: 0.103
C12: Output area:
C15: Share price | D15: =PV(D9,D8,-D7) -> 59.451486

Sheet #8
C1: Chapter 8
C2: Question 8
C4: Input area:
C7: Dividend | D7: 3.25
C8: Share price | D8: 104
C11: Output area:
C14: Required return | D14: =D7/D8 -> 0.03125 | G14: =_xlfn.FORMULATEXT(D14) -> =D7/D8 | I14: Required Return = Dividend/ Share Price

Sheet #9
C1: Chapter 8
C2: Question 9
C4: Input area:
C7: Dividend paid | D7: 3.75
C8: Dividend growth rate | D8: 0.04
C9: Red required return | D9: 0.08
C10: Yellow required return | D10: 0.11
C11: Blue required return | D11: 0.14
C14: Output area:
C17: Red price | D17: =D7/(D9-D8) -> 93.75
C18: Yellow price | D18: =D7/(D10-D8) -> 53.571429
C19: Blue price | D19: =D7/(D11-D8) -> 37.5
C21: As the required return increases, the stock price decreases. This is a function of the time value of money: A higher discount rate decreases the present value of cash flows. It is also important to note that relatively small changes in the required return can have a dramatic impact on the stock price.

Sheet #10
C1: Chapter 8
C2: Question 10
C4: Input area:
C7: Shares outstanding | D7: 840000
C8: Share price | D8: 48
C11: Output area:
C14: Straight voting shares required | D14: =(D7/2)+1 -> 420001
C16: Dollars required in straight voting | D16: =D14*D8 -> 20160048

Sheet #11
C1: Chapter 8
C2: Question 11
C4: Input area:
C7: Shares outstanding | D7: ='#10'!D7 -> 840000
C8: Share price | D8: ='#10'!D8 -> 48
C9: Number of seats | D9: 4
C12: Output area:
C15: Cumulative voting shares required | D15: =((1/(D9+1)*D7)+1) -> 168001
C17: Dollars required in cumulative voting | D17: =D15*D8 -> 8064048

Sheet #12
C1: Chapter 8
C2: Question 12
C4: Input area:
C7: EPS | D7: 5.27
C8: Benchmark PE | D8: 18
C9: Benchmark PE | D9: 21
C12: Output area:
C15: ="Stock price at PE of "&D8 -> Stock price at PE of 18 | D15: =D8*D7 -> 94.86
C16: ="Stock price at PE of "&D9 -> Stock price at PE of 21 | D16: =D9*D7 -> 110.67

Sheet #13
C1: Chapter 8
C2: Question 13
C4: Input area:
C7: Sales | D7: 3100000
C8: Shares outstanding | D8: 175000
C9: Benchmark PS | D9: 3.9
C10: Benchmark PS | D10: 3.1
C13: Output area:
C16: Sales per share | D16: =D7/D8 -> 17.714286
C18: ="Stock price at PS of "&D9 -> Stock price at PS of 3.9 | D18: =D9*D16 -> 69.085714
C19: ="Stock price at PS of "&D10 -> Stock price at PS of 3.1 | D19: =D16*D10 -> 54.914286

Sheet #14
C1: Chapter 8
C2: Question 14
C4: Input area:
C7: Dividend paid | D7: 3.45
C8: Dividend growth rate | D8: 0.034
C10: Required return for first 3 years | D10: 0.15
C11: Required return for second 3 years | D11: 0.13
C12: Final required return | D12: 0.11
C15: Output area:
C18: Stock price at beginning of final period | D18: =(D7*(1+D8)^7)/(D12-D8) -> 57.365301
C19: Stock price at beginning of second period | D19: =(D7*(1+D8)^4/(1+D11))+(D7*(1+D8)^5)/((1+D11)^2)+D7*(1+D8)^6/(1+D11)^3+D18/(1+D11)^3 -> 49.362675
C21: Current stock price | D21: =D7*(1+D8)/(1+D10)+D7*((1+D8)^2)/((1+D10)^2)+D7*(1+D8)^3/(1+D10)^3+D19/(1+D10)^3 -> 40.85563

Sheet #15
C1: Chapter 8
C2: Question 15
C4: Input area:
C7: Future dividend | D7: 18
C8: Years until first dividend | D8: 10
C9: Dividend growth rate | D9: 0.037
C10: Required return | D10: 0.115
C13: Output area:
C16: Stock price at constant growth | D16: =D7/(D10-D9) -> 230.76923
C18: Share price | D18: =PV(D10,D8-1,,-D16) -> 86.637138

Sheet #16
C1: Chapter 8
C2: Question 16
C4: Input area:
C7: Dividend | D7: 4.5
C8: Dividend growth rate | D8: 8
C9: Required return | D9: 0.1
C12: Output area:
C15: Year | D15: Dividend
C16: 1 | D16: =D7+D8 -> 12.5
C17: 2 | D17: =D16+D8 -> 20.5
C18: 3 | D18: =D17+D8 -> 28.5
C19: 4 | D19: =D18+D8 -> 36.5
C20: 5 | D20: =D19+D8 -> 44.5
C22: Share price | D22: =NPV(D9,D16:D20) -> 102.27925

Sheet #17
C1: Chapter 8
C2: Question 17
C4: Input area:
C7: Dividend one | D7: 13
C8: Dividend two | D8: 10
C9: Dividend three | D9: 8
C10: Dividend four | D10: 3.15
C11: Dividend growth rate | D11: 0.04
C12: Required return | D12: 0.105
C15: Output area:
C18: Price after Year 4 dividend | D18: =(D10*(1+D11))/(D12-D11) -> 50.4
C20: Year | D20: Cash flow
C21: 1 | D21: =D7 -> 13
C22: 2 | D22: =D8 -> 10
C23: 3 | D23: =D9 -> 8
C24: 4 | D24: =D10+D18 -> 53.55
C26: Share price | D26: =NPV(D12,D21:D24) -> 61.801695

Sheet #18
C1: Chapter 8
C2: Question 18
C4: Input area:
C7: Dividend growth rate - period 1 | D7: 0.3
C8: Dividend growth rate - period 2 | D8: 0.04
C9: Required return | D9: 0.1
C10: Dividend | D10: 2.95
C13: Output area:
C16: Price at end of high growth | D16: =D10*(1+D7)^3*(1+D8)/(D9-D8) -> 112.33993
C18: Year | D18: Cash flow
C19: 1 | D19: =D10*(1+D7) -> 3.835
C20: 2 | D20: =D19*(1+D7) -> 4.9855
C21: 3 | D21: =D20*(1+D7)+D16 -> 118.82108
C23: Share price | D23: =NPV(D9,D19:D21) -> 96.87865

Sheet #19
C1: Chapter 8
C2: Question 19
C4: Input area:
C7: Initial dividend growth rate | D7: 0.25
C8: Initial number of years | D8: 3
C9: Second growth rate | D9: 0.15
C10: Second number of years | D10: 1
C11: Final growth rate | D11: 0.06
C12: Required return | D12: 0.1
C13: Share price | D13: 94
C16: Output area:
C19: P4 | D19: =(1+D7)^D8*(1+D9)*(1+D11)/(D12-D11) -> 59.521484 | E19: X D0
C21: Share price | D21: =(1+D7)/(1+D12)+(1+D7)^2/(1+D12)^2+(1+D7)^3/(1+D12)^3+((1+D7)^3*(1+D9)+D19)/(1+D12)^4 -> 46.083185 | E21: X D0
C23: Current dividend | D23: =D13/D21 -> 2.0397896
C25: Next year's dividend | D25: =D23*(1+D7) -> 2.549737

Sheet #20
C1: Chapter 8
C2: Question 20
C4: Input area:
C7: Dividend paid | D7: 10.15
C8: Dividend growth rate | D8: -0.03
C9: Required return | D9: 0.095
C12: Output area:
C15: Price | D15: =(D7*(1+D8))/(D9-D8) -> 78.764

Sheet #21
C1: Chapter 8
C2: Question 21
C4: Input area:
C7: Stock price | D7: 53
C8: Required return | D8: 0.12
C9: Dividend growth rate | D9: 0.035
C12: Output area:
C15: Current dividend | D15: =(D7*(D8-D9))/(1+D9) -> 4.352657

Sheet #22
C1: Chapter 8
C2: Question 22
C4: Input area:
C7: Current dividend | D7: 20 | M7: Current dividend | N7: 23
C8: Years until dividend begins | D8: 20 | M8: Years until dividend begins | N8: 12
C9: Required return | D9: 0.057 | M9: Required return | N9: 0.037
C12: Output area: | M12: Output area:
C15: ="Share price at Year "&D8-1 -> Share price at Year 19 | D15: =D7/D9 -> 350.87719 | G15: =_xlfn.FORMULATEXT(D15) -> =D7/D9 | M15: ="Share price at Year "&N8-1 -> Share price at Year 11 | N15: =N7/N9 -> 621.62162 | Q15: =_xlfn.FORMULATEXT(N15) -> =N7/N9
C17: Share price | D17: =PV(D9,D8-1,0,-D15) -> 122.38562 | G17: =_xlfn.FORMULATEXT(D17) -> =PV(D9,D8-1,0,-D15) | M17: Share price | N17: =PV(N9,N8-1,0,-N15) -> 416.83079 | Q17: =_xlfn.FORMULATEXT(N17) -> =PV(N9,N8-1,0,-N15)

Sheet #23
C1: Chapter 8
C2: Question 23
C4: Input area:
C7: Dividend yield | D7: 0.0215 | I7: =D8/D7 -> 95.348837 | M7: =D8/95.35 -> 0.021499738
C8: Dividend paid | D8: 2.05
C9: Change in price | D9: 0.27
C10: PE ratio | D10: 20
C11: Common shares outstanding | D11: 25000000
C14: Output area:
C17: Today's closing price | D17: =D8/D7 -> 95.348837 | G17: =_xlfn.FORMULATEXT(D17) -> =D8/D7 | I17: =Dividend Paid/Dividend Yield | M17: Dividend Yield = Dividend Paid / Closting Price
C19: Yesterday's closing price | D19: =D17-D9 -> 95.078837 | G19: =_xlfn.FORMULATEXT(D19) -> =D17-D9
C21: Earnings per share | D21: =D17/D10 -> 4.7674419 | G21: =_xlfn.FORMULATEXT(D21) -> =D17/D10 | I21: EPS =Closing Price/ PE Ratio | M21: Closing Price = PE Ration * EPS
C23: Net income | D23: =D21*D11 -> 1.1918605e+08 | G23: =_xlfn.FORMULATEXT(D23) -> =D21*D11 | I23: Net Income=EPS *Commonshares Outstanding

Sheet #24
C1: Chapter 8
C2: Question 24
C4: Input Area:
C7: Dividend per share | D7: 2.2
C8: Initial growth rate | D8: 0.24
C9: Terminal growth rate | D9: 0.035
C10: Years of high growth | D10: 8
C11: Required return | D11: 0.12
C14: Output Area:
C17: Stock price | D17: =(((D7*(1+D8))/(D11-D8))*(1-(((1+D8)/(1+D11))^D10)))+((((1+D8)/(1+D11))^D10)*((D7*(1+D9))/(D11-D9))) -> 89.062005 | G17: =_xlfn.FORMULATEXT(D17) -> =(((D7*(1+D8))/(D11-D8))*(1-(((1+D8)/(1+D11))^D10)))+((((1+D8)/(1+D11))^D10)*((D7*(1+D9))/(D11-D9)))

Sheet #25
C1: Chapter 8
C2: Question 25
C4: Input Area:
C7: Initial growth rate | D7: 0.18
C8: Years of high growth | D8: 11
C9: Terminal growth rate | D9: 0.04
C10: Required return | D10: 0.11
C11: Dividend per share | D11: 1.5
C14: Output Area:
C17: Stock price | D17: =(((D11*(1+D7))/(D10-D7))*(1-(((1+D7)/(1+D10))^D8)))+((((1+D7)/(1+D10))^D8)*((D11*(1+D9))/(D10-D9))) -> 67.931368

Sheet #26
C1: Chapter 8
C2: Question 26
C4: Input Area:
C7: EPS | D7: 6.05
C8: Benchmark PE | D8: 21
C9: Earnings growth rate | D9: 0.052
C12: Output Area:
B15: a. | C15: Current stock price | D15: =D8*D7 -> 127.05
B17: b. | C17: Next year's EPS | D17: =D7*(1+D9) -> 6.3646
C19: Target stock price next year | D19: =D17*D8 -> 133.6566
B21: c. | C21: Implicit return | D21: =(D19-D15)/D15 -> 0.052
C23: Notice that the return is the same as the growth rate in earnings. Assuming a stock pays no dividends and the PE ratio is constant, this will always be true when using price ratios to evaluate the price of a share of stock.

Sheet #27
C1: Chapter 8
C2: Question 27
C4: Input Area:
D7: Year 1 | E7: Year 2 | F7: Year 3 | G7: Year 4
C8: Stock price | D8: 58.13 | E8: 62.51 | F8: 68.97 | G8: 74.18
C9: EPS | D9: 2.35 | E9: 2.47 | F9: 2.78 | G9: 3.04
C11: Earnings growth rate | D11: 0.11
C14: Output Area:
D17: Year 1 | E17: Year 2 | F17: Year 3 | G17: Year 4
C18: PE ratio | D18: =D8/D9 -> 24.73617 | E18: =E8/E9 -> 25.307692 | F18: =F8/F9 -> 24.809353 | G18: =G8/G9 -> 24.401316
C20: Average PE | D20: =AVERAGE(D18:G18) -> 24.813633
C21: Next year's EPS | D21: =G9*(1+D11) -> 3.3744
C23: Target stock price next year | D23: =D20*D21 -> 83.731122

Sheet #28
C1: Chapter 8
C2: Question 28
C4: Input Area:
D7: Year 1 | E7: Year 2 | F7: Year 3 | G7: Year 4
C8: High stock price | D8: 62.18 | E8: 67.29 | F8: 74.18 | G8: 78.27
C9: Low stock price | D9: 40.3 | E9: 43.18 | F9: 39.27 | G9: 46.21
C10: EPS | D10: 2.35 | E10: 2.58 | F10: 2.73 | G10: 2.89
C12: Earnings growth rate | D12: 0.09
C15: Output Area:
D18: Year 1 | E18: Year 2 | F18: Year 3 | G18: Year 4
C19: High PE ratio | D19: =D8/D10 -> 26.459574 | E19: =E8/E10 -> 26.081395 | F19: =F8/F10 -> 27.172161 | G19: =G8/G10 -> 27.083045
C20: Low PE ratio | D20: =D9/D10 -> 17.148936 | E20: =E9/E10 -> 16.736434 | F20: =F9/F10 -> 14.384615 | G20: =G9/G10 -> 15.989619
C22: Average high PE ratio | D22: =AVERAGE(D19:G19) -> 26.699044
C23: Average low PE ratio | D23: =AVERAGE(D20:G20) -> 16.064901
C25: Next year's EPS | D25: =G10*(1+D12) -> 3.1501
C27: High target stock price next year | D27: =D22*D25 -> 84.104658
C28: Low target stock price next year | D28: =D23*D25 -> 50.606045

Sheet #29
C1: Chapter 8
C2: Question 29
C4: Input Area:
C7: EPS | D7: 2.85
C8: Earnings growth rate | D8: 0.08
C9: Benchmark PE | D9: 19
C10: Year for target stock price | D10: 5
C13: Output Area:
C16: ="Projected EPS in "&D10&" years" -> Projected EPS in 5 years | D16: =FV(D8,D10,,-D7) -> 4.187585
C18: ="Target stock price in "&D10&" years" -> Target stock price in 5 years | D18: =D16*D9 -> 79.564115

Sheet #30
C1: Chapter 8
C2: Question 30
C4: Input area:
C7: Dividend | D7: 1.87
C8: Dividend growth rate | D8: 0.13
C9: Years of growth | D9: 5
C10: Terminal payout ratio | D10: 0.3
C11: Benchmark PE | D11: 19
C12: Required return | D12: 0.11
C15: Output area:
C18: ="EPS in "&D9&" years" -> EPS in 5 years | D18: =D26/D10 -> 11.484513
C19: ="Stock price in "&D9&" years" -> Stock price in 5 years | D19: =D18*D11 -> 218.20574
C21: Year | D21: Dividend | E21: Terminal price | F21: Present value
C22: 1 | D22: =D7*(1+D8) -> 2.1131 | F22: =PV($D$12,C22,,-D22-E22) -> 1.9036937
C23: 2 | D23: =D22*(1+$D$8) -> 2.387803 | F23: =PV($D$12,C23,,-D23-E23) -> 1.9379945
C24: 3 | D24: =D23*(1+$D$8) -> 2.6982174 | F24: =PV($D$12,C24,,-D24-E24) -> 1.9729133
C25: 4 | D25: =D24*(1+$D$8) -> 3.0489857 | F25: =PV($D$12,C25,,-D25-E25) -> 2.0084613
C26: 5 | D26: =D25*(1+$D$8) -> 3.4453538 | E26: =IF($D$9=C26,$D$19,0) -> 218.20574 | F26: =PV($D$12,C26,,-D26-E26) -> 131.53914
C28: Share price | D28: =SUM(F22:F26) -> 139.3622

Sheet #31
C1: Chapter 8
C2: Question 31
C4: Input Area:
C7: Equity | D7: 8400000
C8: Net income | D8: 832000
C9: Dividends | D9: 285000
C10: Shares outstanding | D10: 215000
C11: Benchmark PE | D11: 16
C14: Output Area:
C17: ROE | D17: =D8/D7 -> 0.099047619
C18: Retention ratio | D18: =1-(D9/D8) -> 0.65745192
C19: Sustainable growth rate | D19: =(D17*D18)/(1-(D17*D18)) -> 0.069654909
C20: Current EPS | D20: =D8/D10 -> 3.8697674
C21: EPS in one year | D21: =D20*(1+D19) -> 4.1393157
C23: Target stock price in one year | D23: =D21*D11 -> 66.229052

Sheet #32
C1: Chapter 8
C2: Question 32
C4: Input area:
C7: Required return | D7: 0.12
C8: Most recent dividend | D8: 4.25
C10: Stock W dividend growth rate | D10: 0.1
C11: Stock X dividend growth rate | D11: 0
C12: Stock Y dividend growth rate | D12: -0.05
C14: Stock Z:
C15: Initial growth rate | D15: 0.2
C16: Initial years of growth | D16: 2
C17: Final growth rate | D17: 0.05
C20: Output area:
C23: Dividend yields:
C24: Stock W price | D24: =D8*(1+D10)/(D7-D10) -> 233.75
C25: Dividend yield | D25: =D8*(1+D10)/D24 -> 0.02 | I25: =_xlfn.FORMULATEXT(D25) -> =D8*(1+D10)/D24
C26: Capital gains yield | D26: =D7-D25 -> 0.1 | I26: =_xlfn.FORMULATEXT(D26) -> =D7-D25
C28: Stock X price | D28: =D8/(D7-D11) -> 35.416667 | I28: =_xlfn.FORMULATEXT(D28) -> =D8/(D7-D11)
C29: Dividend yield | D29: =D8*(1+D11)/D28 -> 0.12 | I29: =_xlfn.FORMULATEXT(D29) -> =D8*(1+D11)/D28
C30: Capital gains yield | D30: =D7-D29 -> 0 | I30: =_xlfn.FORMULATEXT(D30) -> =D7-D29
C32: Stock Y price | D32: =D8*(1+D12)/(D7-D12) -> 23.75 | I32: =_xlfn.FORMULATEXT(D32) -> =D8*(1+D12)/(D7-D12)
C33: Dividend yield | D33: =D8*(1+D12)/D32 -> 0.17 | I33: =_xlfn.FORMULATEXT(D33) -> =D8*(1+D12)/D32
C34: Capital gains yield | D34: =D7-D33 -> -0.05 | I34: =_xlfn.FORMULATEXT(D34) -> =D7-D33
C36: Stock Z price at final rate | D36: =D8*(1+D15)^D16*(1+D17)/(D7-D17) -> 91.8 | I36: =_xlfn.FORMULATEXT(D36) -> =D8*(1+D15)^D16*(1+D17)/(D7-D17)
C37: Stock Z current price | D37: =D8*(1+D15)/(1+D7)+D8*(1+D15)^D16/(1+D7)^D16+D36/(1+D7)^2 -> 82.614796 | I37: =_xlfn.FORMULATEXT(D37) -> =D8*(1+D15)/(1+D7)+D8*(1+D15)^D16/(1+D7)^D16+D36/(1+D7)^2
C38: Dividend yield | D38: =D8*(1+D15)/D37 -> 0.061732283 | I38: =_xlfn.FORMULATEXT(D38) -> =D8*(1+D15)/D37
C39: Capital gains yield | D39: =D7-D38 -> 0.058267717 | I39: =_xlfn.FORMULATEXT(D39) -> =D7-D38
C43: In all cases, the required return is 12%, but this return is distributed differently between current income and capital gains. High growth stocks have an appreciable capital gains component but a relatively small current income yield; conversely, mature, negative growth stocks provide a high current income but also price depreciation over time.

Sheet #33
C1: Chapter 8
C2: Question 33
C4: Input area:
C7: Dividend paid (D0) | D7: 3.8
C8: Dividend growth rate (g)) | D8: 0.034
C9: Required return ('r) | D9: 0.105
C11: Dividends per year (Qtrly) | D11: 4
C14: Output area:
B17: a. | C17: Price | D17: =(D7*(1+D8))/(D9-D8) -> 55.340845 | G17: =_xlfn.FORMULATEXT(D17) -> =(D7*(1+D8))/(D9-D8) | I17: =D0*(1+g)/(r-g)
B19: b. | C19: Next four dividends | D19: =D7*(1+D8)/D11 -> 0.9823 | G19: =_xlfn.FORMULATEXT(D19) -> =D7*(1+D8)/D11 | I19: =D0*(1+g)/ Dividend Per Year
C20: Effective quarterly rate | D20: =(1+D9)^(1/D11)-1 -> 0.025275476 | G20: =_xlfn.FORMULATEXT(D20) -> =(1+D9)^(1/D11)-1 | I20: =(1+r)^(1/DivperYear) -1
C21: Effective first dividend | D21: =FV(D20,D11,-D19) -> 4.0806946 | G21: =_xlfn.FORMULATEXT(D21) -> =FV(D20,D11,-D19)
C23: Share price | D23: =D21/(D9-D8) -> 57.474572 | G23: =_xlfn.FORMULATEXT(D23) -> =D21/(D9-D8)

Sheet #34, 35
C1: Chapter 8
C2: Questions 34, 35
C4: Input area:
C7: Required return | D7: 0.11
C8: Most recent dividend | D8: 4.1
C10: Year 1 dividend growth rate | D10: 0.2
C11: Year 2 dividend growth rate | D11: 0.15
C12: Year 3 dividend growth rate | D12: 0.1
C13: Year 4 dividend growth rate | D13: 0.05
C16: Output area:
C19: Share price after Year 3 dividend | D19: =D8*(1+D10)*(1+D11)*(1+D12)*(1+D13)/((D7-D13)) -> 108.9165 | G19: =_xlfn.FORMULATEXT(D19) -> =D8*(1+D10)*(1+D11)*(1+D12)*(1+D13)/((D7-D13))
C21: Share price | D21: =D8*(1+D10)/(1+D7)+D8*(1+D10)*(1+D11)/(1+D7)^2+D8*(1+D10)*(1+D11)*(1+D12)/(1+D7)^3+(D19/(1+D7)^3) -> 93.214187 | G21: =_xlfn.FORMULATEXT(D21) -> =D8*(1+D10)/(1+D7)+D8*(1+D10)*(1+D11)/(1+D7)^2+D8*(1+D10)*(1+D11)*(1+D12)/(1+D7)^3+(D19/(1+D7)^3)
C25: To solve Problem #35, adjust the required return until the share price is equal to $67.25. Alternatively, you could use the "Solver" or "Goal Seek" functions as we did.

Sheet #35 Answer Report
A1: Microsoft Excel 16.0 Answer Report
A2: Worksheet: [FCF 14th edition Chapter 08.xlsx]#34, 35
A3: Report Created: 2/18/2023 5:55:21 PM
A4: Result: Solver found a solution. All Constraints and optimality conditions are satisfied.
A5: Solver Engine
B6: Engine: GRG Nonlinear
B7: Solution Time: 0.031 Seconds.
B8: Iterations: 1 Subproblems: 0
A9: Solver Options
B10: Max Time 100 sec, Iterations 100, Precision 0.000001
B11: Convergence 0.0001, Population Size 100, Random Seed 0, Derivatives Forward, Require Bounds
B12: Max Subproblems Unlimited, Max Integer Sols Unlimited, Integer Tolerance 5%, Solve Without Integer Constraints
A14: Objective Cell (Value Of)
B15: Cell | C15: Name | D15: Original Value | E15: Final Value
B16: $D$21 | C16: Share price | D16: 93.2142 | E16: 84.25
A19: Variable Cells
B20: Cell | C20: Name | D20: Original Value | E20: Final Value | F20: Integer
B21: $D$7 | C21: Required return | D21: 0.11 | E21: 0.1163234 | F21: Contin
A24: Constraints
B25: Cell | C25: Name | D25: Cell Value | E25: Formula | F25: Status | G25: Slack
B26: $D$21 | C26: Share price | D26: 84.25 | E26: $D$21=84.25 | F26: Binding | G26: 0
