Workbook

Sheet Instructions
B1: BUS 311 | Chapter 14 — Equity Account Analysis
B2: ABC Industrial Corp. — Student Workbook
B4: COLOR KEY
B5: CREAM cells | C5: Enter your formula or value here — student input required
B6: ICE BLUE cells | C6: Given data — do not edit
B7: CREAM cells | C7: Final answer cells — populated by your formulas
B8: WHITE cells | C8: Intermediate formula cells
B10: LEARNING OBJECTIVES
B11: 1. Identify and define each component of the shareholders' equity section
B12: 2. Calculate authorized, issued, treasury, and outstanding share counts
B13: 3. Compute par value, additional paid-in capital, and net common equity
B14: 4. Determine book value per share
B15: 5. Analyze the impact of a new share issuance and a share repurchase on the equity section
B17: WORKSHEET NAVIGATION
B18: Instructions | C18: This sheet — overview, color key, objectives
B19: Company Data | C19: ABC Industrial Corp. given data — read only
B20: Part 1 - Base Analysis | C20: Equity section before any transactions
B21: Part 2 - New Issuance | C21: Impact of issuing 5,000 new shares at $25
B22: Part 3 - Buyback | C22: Impact of repurchasing 2,000 additional shares at $23
B23: Part 4 - Summary | C23: Side-by-side comparison of all three equity sections

Sheet Company Data
B1: ABC INDUSTRIAL CORP. — GIVEN DATA
B2: All data below is given — do not edit these cells. Refer to this sheet from the analysis tabs.
B4: Section 1 — Corporate Charter
B5: Authorized Shares | C5: 100000 | D5: Maximum shares allowed without shareholder vote
B6: Par Value per Share | C6: 1 | D6: Nominal value per share at issuance
B8: Section 2 — Share Issuance & Repurchase History
B9: Shares Issued (IPO) | C9: 60000 | D9: Shares sold to investors at IPO
B10: IPO Price per Share | C10: 18 | D10: Price at which shares were first sold
B11: Treasury Shares (repurchased) | C11: 4000 | D11: Shares bought back by company
B12: Treasury Stock Cost per Share | C12: 22 | D12: Price paid per repurchased share
B14: Section 3 — Retained Earnings
B15: Retained Earnings (cumulative) | C15: 485000 | D15: Given — cumulative net income less dividends paid
B17: Section 4 — Proposed Transactions (Parts 2 & 3)
B18: New Shares to Issue (Part 2) | C18: 5000 | D18: New equity issuance
B19: New Issue Price per Share | C19: 25 | D19: Offering price for new shares
B20: Additional Buyback Shares (Pt 3) | C20: 2000 | D20: Additional repurchase
B21: Additional Buyback Price | C21: 23 | D21: Price per additional repurchased share
B23: Source: Simulated data for instructional purposes — ABC Industrial Corp. is a fictional company

Sheet Part 1 - Base Analysis
B1: PART 1 — BASE EQUITY ANALYSIS
B2: ABC Industrial Corp. | Equity Section BEFORE Any New Transactions
B4: Section A — Share Count Analysis
B5: Item | C5: Shares | D5: Notes
B6: Authorized Shares | C6: ='Company Data'!C5 -> 100000 | D6: From corporate charter
B7: Shares Issued | C7: ='Company Data'!C9 -> 60000 | D7: Sold to investors at IPO
B8: Treasury Shares | C8: ='Company Data'!C11 -> 4000 | D8: Repurchased by company
B9: Shares Outstanding | D9: Issued minus treasury
B10: Shares Available to Issue | D10: Authorized minus issued
B12: Section B — Shareholders' Equity Section
B13: Account | C13: Amount ($) | D13: Formula / Notes
B14: Common Stock (Par Value) | C14: ='Company Data'!C9*'Company Data'!C6 -> 60000 | D14: Issued shares × par value per share
B15: Additional Paid-In Capital | C15: =('Company Data'!C10-'Company Data'!C6)*'Company Data'!C9 -> 1020000 | D15: (IPO price − par) × shares issued
B16: Retained Earnings | C16: ='Company Data'!C15 -> 485000 | D16: Given — cumulative retained profits
B17: Treasury Stock (contra) | C17: =-('Company Data'!C11*'Company Data'!C12) -> -88000 | D17: Treasury shares × cost — negative
B18: Net Common Equity | D18: Sum of all equity components
B20: Section C — Book Value Per Share
B21: Book Value per Share | D21: Net equity ÷ shares outstanding
B23: HINT: All formulas should reference 'Company Data' tab cells — do not hardcode numbers.

Sheet Part 2 - New Issuance
B1: PART 2 — IMPACT OF NEW SHARE ISSUANCE
B2: ABC issues 5,000 NEW shares at $25.00 per share — reconstruct the equity section
B4: Section A — Updated Share Count
B5: Item | C5: Shares | D5: Notes
B6: Original Shares Issued | C6: ='Company Data'!C9 -> 60000 | D6: From Part 1
B7: New Shares Issued | C7: ='Company Data'!C18 -> 5000 | D7: Proposed new issuance
B8: Total Shares Issued (updated) | D8: Original + new
B9: Treasury Shares | C9: ='Company Data'!C11 -> 4000 | D9: Unchanged
B10: Shares Outstanding (updated) | D10: Updated issued minus treasury
B12: Section B — Updated Equity Section After Issuance
B13: Account | C13: Amount ($) | D13: Formula / Notes
B14: Common Stock (Par Value) | C14: =C8*'Company Data'!C6 -> 0 | D14: Total issued shares × par value
B15: Additional Paid-In Capital | C15: =('Company Data'!C10-'Company Data'!C6)*'Company Data'!C9+('Company Data'!C19-'Company Data'!C6)*'Company Data'!C18 -> 1140000 | D15: Original APIC + new shares APIC
B16: Retained Earnings | C16: ='Company Data'!C15 -> 485000 | D16: Unchanged
B17: Treasury Stock (contra) | C17: =-('Company Data'!C11*'Company Data'!C12) -> -88000 | D17: Unchanged
B18: Net Common Equity (updated) | D18: Sum of all components
B20: Section C — Book Value Per Share After Issuance
B21: Book Value per Share (updated) | D21: Net equity ÷ updated shares outstanding
B23: THINK: Did book value per share go up or down compared to Part 1? Why?

Sheet Part 3 - Buyback
B1: PART 3 — IMPACT OF ADDITIONAL SHARE REPURCHASE
B2: Starting from Part 1 (base) — ABC repurchases 2,000 MORE shares at $23.00
B4: Section A — Updated Share Count After Buyback
B5: Item | C5: Shares | D5: Notes
B6: Shares Issued | C6: ='Company Data'!C9 -> 60000 | D6: Unchanged from Part 1
B7: Original Treasury Shares | C7: ='Company Data'!C11 -> 4000 | D7: From Part 1
B8: Additional Treasury Shares | C8: ='Company Data'!C20 -> 2000 | D8: New repurchase
B9: Total Treasury Shares | D9: Combined repurchases
B10: Shares Outstanding (updated) | D10: Issued minus total treasury
B12: Section B — Updated Equity Section After Buyback
B13: Account | C13: Amount ($) | D13: Formula / Notes
B14: Common Stock (Par Value) | C14: ='Company Data'!C9*'Company Data'!C6 -> 60000 | D14: Issued shares × par — unchanged
B15: Additional Paid-In Capital | C15: =('Company Data'!C10-'Company Data'!C6)*'Company Data'!C9 -> 1020000 | D15: Unchanged from Part 1
B16: Retained Earnings | C16: ='Company Data'!C15 -> 485000 | D16: Unchanged
B17: Treasury Stock (contra) | C17: =-(C7*'Company Data'!C12+C8*'Company Data'!C21) -> -134000 | D17: Original + new repurchase at different prices
B18: Net Common Equity (updated) | D18: Sum of all components
B20: Section C — Book Value Per Share After Buyback
B21: Book Value per Share (updated) | D21: Net equity ÷ updated outstanding shares
B23: THINK: Why does treasury stock use the actual cost paid — not par value?

Sheet Part 4 - Summary
B1: PART 4 — SIDE-BY-SIDE COMPARISON
B2: Compare all three equity sections — Base, After Issuance, After Buyback
B4: Account / Metric | C4: Base (Part 1) | D4: After Issuance (Part 2) | E4: After Buyback (Part 3) | F4: Key Observation
B5: Shares Outstanding | F5: Issuance ↑ outstanding; buyback ↓ outstanding
B6: Common Stock (Par Value) | F6: Par value changes with new issuance
B7: Additional Paid-In Capital | F7: APIC rises with new issuance; unchanged in buyback
B8: Retained Earnings | F8: Unchanged in both scenarios (no income/dividends)
B9: Treasury Stock (contra) | F9: Buyback increases the contra-equity deduction
B10: NET COMMON EQUITY | F10: Issuance raises equity; buyback reduces it
B11: Book Value per Share | F11: Issuance below BV/share (↓ to $26.26) dilutes existing shareholders; buyback below BV/share (↑ to $26.50) is accretive
B13: REFLECTION: The issuance price ($25) is above book value per share from Part 1. Does this increase or decrease the book value per share for existing shareholders? The buyback price ($23) — is it above or below book value? What is the effect? Use your calculated values to explain your reasoning.
