Workbook
Name WACC: Inputs!$B$25

Sheet Instructions
A1: 📘 Corporate Project Decision Activity (WACC & Metrics)
A3: Objective
A4: Use weighted average cost of capital (WACC) and project appraisal metrics (NPV, IRR, MIRR, Payback, Discounted Payback, Profitability Index) to decide which project(s) a corporation should undertake.
A6: What you will do
A7: 1) Go to the 'Inputs' sheet and set capital structure & rate assumptions (risk‑free rate, beta, market risk premium, tax rate, etc.).
A8: 2) Verify the WACC that is calculated automatically.
A9: 3) Go to the 'Projects' sheet. Review three sample projects and their cash flows
A10: 4) The sheet computes NPV, IRR, MIRR, Payback, Discounted Payback and PI for each project using the WACC as the hurdle rate.
A11: 5) Decide which project(s) to accept. Then perform sensitivity checks: change beta by +0.20, tax rate by +10pp, or market risk premium by +1pp and observe the impact on rankings.
A13: Deliverables (suggested)
A14: • Report the calculated WACC.
A15: • Identify which project(s) you accept and justify using at least two metrics (e.g., NPV and IRR).
... A22: • MIRR assumes reinvestment at the WACC and can be more realistic than IRR.

Sheet Inputs
A1: Corporate Finance Inputs
A3: Risk-free rate (Rf) | B3: 0.04
A4: Market risk premium (MRP) | B4: 0.05
A5: Equity beta (β) | B5: 1.2
A6: Cost of Equity (k_e) = Rf + β×MRP | B6: =B3 + B5*B4 -> 0.1
A8: Preferred dividend (per share) | B8: 2
A9: Preferred stock price | B9: 25
A10: Cost of Preferred (k_p) = Dividend / Price | B10: =B8/B9 -> 0.08
A12: Pre-tax cost of debt (k_d) | B12: 0.06
A13: Tax rate (T) | B13: 0.25
A14: After-tax cost of debt k_d(1-T) | B14: =B12*(1-B13) -> 0.045
A16: Market value of Debt | B16: 300000
A17: Market value of Equity | B17: 500000
A18: Market value of Preferred | B18: 50000
A19: Total market value | B19: =SUM(B16:B18) -> 850000
A21: Weight of Debt (wD) | B21: =B16/B19 -> 0.35294118
A22: Weight of Equity (wE) | B22: =B17/B19 -> 0.58823529
A23: Weight of Preferred (wP) | B23: =B18/B19 -> 0.058823529
A25: WACC = wD*k_d(1-T) + wE*k_e + wP*k_p | B25: =B21*B14 + B22*B6 + B23*B10 -> 0.079411765

Sheet Projects
A1: Project | B1: Initial Outlay | C1: Year1 | D1: Year2 | E1: Year3 | F1: Year4 | G1: Year5 | H1: Cum0 | I1: Cum1 | J1: Cum2 | K1: Cum3 | L1: Cum4 | M1: Cum5 | N1: DCash1 | O1: DCash2 | P1: DCash3 | Q1: DCash4 | R1: DCash5 | S1: DCum0 | T1: DCum1 | U1: DCum2 | V1: DCum3 | W1: DCum4 | X1: DCum5 | Y1: NPV | Z1: IRR | AA1: MIRR | AB1: PI | AC1: Payback | AD1: DPayback | AE1: Decision
A2: Project A | B2: -100000 | C2: 25000 | D2: 30000 | E2: 35000 | F2: 40000 | G2: 45000 | H2: =tblProjects[[#This Row],[Initial Outlay]] -> -100000 | I2: =tblProjects[[#This Row],[Cum0]]+tblProjects[[#This Row],[Year1]] -> -75000 | J2: =tblProjects[[#This Row],[Cum1]]+tblProjects[[#This Row],[Year2]] -> -45000 | K2: =tblProjects[[#This Row],[Cum2]]+tblProjects[[#This Row],[Year3]] -> -10000 | L2: =tblProjects[[#This Row],[Cum3]]+tblProjects[[#This Row],[Year4]] -> 30000 | M2: =tblProjects[[#This Row],[Cum4]]+tblProjects[[#This Row],[Year5]] -> 75000 | N2: =tblProjects[[#This Row],[Year1]]/(1+WACC)^1 -> 23160.763 | O2: =tblProjects[[#This Row],[Year2]]/(1+WACC)^2 -> 25748.205 | P2: =tblProjects[[#This Row],[Year3]]/(1+WACC)^3 -> 27829.577 | Q2: =tblProjects[[#This Row],[Year4]]/(1+WACC)^4 -> 29465.336 | R2: =tblProjects[[#This Row],[Year5]]/(1+WACC)^5 -> 30709.785 | S2: =tblProjects[[#This Row],[Initial Outlay]] -> -100000 | T2: =tblProjects[[#This Row],[DCum0]]+tblProjects[[#This Row],[DCash1]] -> -76839.237 | U2: =tblProjects[[#This Row],[DCum1]]+tblProjects[[#This Row],[DCash2]] -> -51091.032 | V2: =tblProjects[[#This Row],[DCum2]]+tblProjects[[#This Row],[DCash3]] -> -23261.455 | W2: =tblProjects[[#This Row],[DCum3]]+tblProjects[[#This Row],[DCash4]] -> 6203.8812 | X2: =tblProjects[[#This Row],[DCum4]]+tblProjects[[#This Row],[DCash5]] -> 36913.666 | Y2: =NPV(WACC, tblProjects[[#This Row],[Year1]]:tblProjects[[#This Row],[Year5]]) + tblProjects[[#This Row],[Initial Outlay]] -> 36913.666 | Z2: =IRR(tblProjects[[#This Row],[Initial Outlay]]:tblProjects[[#This Row],[Year5]]) -> 0.19711108 | AA2: =MIRR(tblProjects[[#This Row],[Initial Outlay]]:tblProjects[[#This Row],[Year5]], WACC, WACC) -> 0.14941407 | AB2: =NPV(WACC, tblProjects[[#This Row],[Year1]]:tblProjects[[#This Row],[Year5]])/ABS(tblProjects[[#This Row],[Initial Outlay]]) -> 1.3691367 | AC2: {=_xlfn.LET(_xlpm.c, tblProjects[[#This Row],[Cum0]]:tblProjects[[#This Row],[Cum5]], _xlpm.k, _xlfn.XMATCH(TRUE, _xlpm.c>=0, 0), IF(ISNUMBER(_xlpm.k), IF(_xlpm.k=1, 0, (_xlpm.k-1) + (-INDEX(_xlpm.c,1,_xlpm.k-1))/INDEX(tblProjects[[#This Row],[Year1]]:tblProjects[[#This Row],[Year5]],1,_xlpm.k-1)), "No PB"))} -> 4.25 | AD2: {=_xlfn.LET(_xlpm.c, tblProjects[[#This Row],[DCum0]]:tblProjects[[#This Row],[DCum5]], _xlpm.f, tblProjects[[#This Row],[DCash1]]:tblProjects[[#This Row],[DCash5]], _xlpm.k, _xlfn.XMATCH(TRUE, _xlpm.c>=0, 0), IF(ISNUMBER(_xlpm.k), IF(_xlpm.k=1, 0, (_xlpm.k-1) + (-INDEX(_xlpm.c,1,_xlpm.k-1))/INDEX(_xlpm.f,1,_xlpm.k-1)), "No DPB"))} -> 4.7894515 | AE2: =IF(AND(tblProjects[[#This Row],[NPV]]>0, tblProjects[[#This Row],[IRR]]>WACC, tblProjects[[#This Row],[PI]]>1), "ACCEPT", "REJECT") -> ACCEPT
A3: Project B | B3: -120000 | C3: 20000 | D3: 30000 | E3: 40000 | F3: 50000 | G3: 55000 | H3: =tblProjects[[#This Row],[Initial Outlay]] -> -120000 | I3: =tblProjects[[#This Row],[Cum0]]+tblProjects[[#This Row],[Year1]] -> -100000 | J3: =tblProjects[[#This Row],[Cum1]]+tblProjects[[#This Row],[Year2]] -> -70000 | K3: =tblProjects[[#This Row],[Cum2]]+tblProjects[[#This Row],[Year3]] -> -30000 | L3: =tblProjects[[#This Row],[Cum3]]+tblProjects[[#This Row],[Year4]] -> 20000 | M3: =tblProjects[[#This Row],[Cum4]]+tblProjects[[#This Row],[Year5]] -> 75000 | N3: =tblProjects[[#This Row],[Year1]]/(1+WACC)^1 -> 18528.61 | O3: =tblProjects[[#This Row],[Year2]]/(1+WACC)^2 -> 25748.205 | P3: =tblProjects[[#This Row],[Year3]]/(1+WACC)^3 -> 31805.231 | Q3: =tblProjects[[#This Row],[Year4]]/(1+WACC)^4 -> 36831.67 | R3: =tblProjects[[#This Row],[Year5]]/(1+WACC)^5 -> 37534.182 | S3: =tblProjects[[#This Row],[Initial Outlay]] -> -120000 | T3: =tblProjects[[#This Row],[DCum0]]+tblProjects[[#This Row],[DCash1]] -> -101471.39 | U3: =tblProjects[[#This Row],[DCum1]]+tblProjects[[#This Row],[DCash2]] -> -75723.185 | V3: =tblProjects[[#This Row],[DCum2]]+tblProjects[[#This Row],[DCash3]] -> -43917.954 | W3: =tblProjects[[#This Row],[DCum3]]+tblProjects[[#This Row],[DCash4]] -> -7086.2835 | X3: =tblProjects[[#This Row],[DCum4]]+tblProjects[[#This Row],[DCash5]] -> 30447.898 | Y3: =NPV(WACC, tblProjects[[#This Row],[Year1]]:tblProjects[[#This Row],[Year5]]) + tblProjects[[#This Row],[Initial Outlay]] -> 30447.898 | Z3: =IRR(tblProjects[[#This Row],[Initial Outlay]]:tblProjects[[#This Row],[Year5]]) -> 0.15685673 | AA3: =MIRR(tblProjects[[#This Row],[Initial Outlay]]:tblProjects[[#This Row],[Year5]], WACC, WACC) -> 0.12934887 | AB3: =NPV(WACC, tblProjects[[#This Row],[Year1]]:tblProjects[[#This Row],[Year5]])/ABS(tblProjects[[#This Row],[Initial Outlay]]) -> 1.2537325 | AC3: {=_xlfn.LET(_xlpm.c, tblProjects[[#This Row],[Cum0]]:tblProjects[[#This Row],[Cum5]], _xlpm.k, _xlfn.XMATCH(TRUE, _xlpm.c>=0, 0), IF(ISNUMBER(_xlpm.k), IF(_xlpm.k=1, 0, (_xlpm.k-1) + (-INDEX(_xlpm.c,1,_xlpm.k-1))/INDEX(tblProjects[[#This Row],[Year1]]:tblProjects[[#This Row],[Year5]],1,_xlpm.k-1)), "No PB"))} -> 4.6 | AD3: {=_xlfn.LET(_xlpm.c, tblProjects[[#This Row],[DCum0]]:tblProjects[[#This Row],[DCum5]], _xlpm.f, tblProjects[[#This Row],[DCash1]]:tblProjects[[#This Row],[DCash5]], _xlpm.k, _xlfn.XMATCH(TRUE, _xlpm.c>=0, 0), IF(ISNUMBER(_xlpm.k), IF(_xlpm.k=1, 0, (_xlpm.k-1) + (-INDEX(_xlpm.c,1,_xlpm.k-1))/INDEX(_xlpm.f,1,_xlpm.k-1)), "No DPB"))} -> 5.1887955 | AE3: =IF(AND(tblProjects[[#This Row],[NPV]]>0, tblProjects[[#This Row],[IRR]]>WACC, tblProjects[[#This Row],[PI]]>1), "ACCEPT", "REJECT") -> ACCEPT
A4: Project C | B4: -80000 | C4: 22000 | D4: 24000 | E4: 26000 | F4: 30000 | G4: 35000 | H4: =tblProjects[[#This Row],[Initial Outlay]] -> -80000 | I4: =tblProjects[[#This Row],[Cum0]]+tblProjects[[#This Row],[Year1]] -> -58000 | J4: =tblProjects[[#This Row],[Cum1]]+tblProjects[[#This Row],[Year2]] -> -34000 | K4: =tblProjects[[#This Row],[Cum2]]+tblProjects[[#This Row],[Year3]] -> -8000 | L4: =tblProjects[[#This Row],[Cum3]]+tblProjects[[#This Row],[Year4]] -> 22000 | M4: =tblProjects[[#This Row],[Cum4]]+tblProjects[[#This Row],[Year5]] -> 57000 | N4: =tblProjects[[#This Row],[Year1]]/(1+WACC)^1 -> 20381.471 | O4: =tblProjects[[#This Row],[Year2]]/(1+WACC)^2 -> 20598.564 | P4: =tblProjects[[#This Row],[Year3]]/(1+WACC)^3 -> 20673.4 | Q4: =tblProjects[[#This Row],[Year4]]/(1+WACC)^4 -> 22099.002 | R4: =tblProjects[[#This Row],[Year5]]/(1+WACC)^5 -> 23885.388 | S4: =tblProjects[[#This Row],[Initial Outlay]] -> -80000 | T4: =tblProjects[[#This Row],[DCum0]]+tblProjects[[#This Row],[DCash1]] -> -59618.529 | U4: =tblProjects[[#This Row],[DCum1]]+tblProjects[[#This Row],[DCash2]] -> -39019.965 | V4: =tblProjects[[#This Row],[DCum2]]+tblProjects[[#This Row],[DCash3]] -> -18346.565 | W4: =tblProjects[[#This Row],[DCum3]]+tblProjects[[#This Row],[DCash4]] -> 3752.4377 | X4: =tblProjects[[#This Row],[DCum4]]+tblProjects[[#This Row],[DCash5]] -> 27637.826 | Y4: =NPV(WACC, tblProjects[[#This Row],[Year1]]:tblProjects[[#This Row],[Year5]]) + tblProjects[[#This Row],[Initial Outlay]] -> 27637.826 | Z4: =IRR(tblProjects[[#This Row],[Initial Outlay]]:tblProjects[[#This Row],[Year5]]) -> 0.19253225 | AA4: =MIRR(tblProjects[[#This Row],[Initial Outlay]]:tblProjects[[#This Row],[Year5]], WACC, WACC) -> 0.14541307 | AB4: =NPV(WACC, tblProjects[[#This Row],[Year1]]:tblProjects[[#This Row],[Year5]])/ABS(tblProjects[[#This Row],[Initial Outlay]]) -> 1.3454728 | AC4: {=_xlfn.LET(_xlpm.c, tblProjects[[#This Row],[Cum0]]:tblProjects[[#This Row],[Cum5]], _xlpm.k, _xlfn.XMATCH(TRUE, _xlpm.c>=0, 0), IF(ISNUMBER(_xlpm.k), IF(_xlpm.k=1, 0, (_xlpm.k-1) + (-INDEX(_xlpm.c,1,_xlpm.k-1))/INDEX(tblProjects[[#This Row],[Year1]]:tblProjects[[#This Row],[Year5]],1,_xlpm.k-1)), "No PB"))} -> 4.2666667 | AD4: {=_xlfn.LET(_xlpm.c, tblProjects[[#This Row],[DCum0]]:tblProjects[[#This Row],[DCum5]], _xlpm.f, tblProjects[[#This Row],[DCash1]]:tblProjects[[#This Row],[DCash5]], _xlpm.k, _xlfn.XMATCH(TRUE, _xlpm.c>=0, 0), IF(ISNUMBER(_xlpm.k), IF(_xlpm.k=1, 0, (_xlpm.k-1) + (-INDEX(_xlpm.c,1,_xlpm.k-1))/INDEX(_xlpm.f,1,_xlpm.k-1)), "No DPB"))} -> 4.8301988 | AE4: =IF(AND(tblProjects[[#This Row],[NPV]]>0, tblProjects[[#This Row],[IRR]]>WACC, tblProjects[[#This Row],[PI]]>1), "ACCEPT", "REJECT") -> ACCEPT

Sheet Sheet1
A1: Project A → NPV: $36,913.67 | IRR: 19.71% | MIRR: 14.94% | PI: 1.37 | Payback: 4.25 yrs | D-Payback: 4.79 yrs | Decision: ACCEPT
A2: Project B → NPV: $30,447.90 | IRR: 15.69% | MIRR: 12.93% | PI: 1.25 | Payback: 4.60 yrs | D-Payback: 5.19 yrs | Decision: ACCEPT
A3: Project C → NPV: $27,637.83 | IRR: 19.25% | MIRR: 14.54% | PI: 1.35 | Payback: 4.27 yrs | D-Payback: 4.83 yrs | Decision: ACCEPT

Sheet Sensitivity
A1: WACC vs Beta (holding other inputs constant) | D1: WACC vs Market Risk Premium | H1: NPV vs WACC (select project)
A2: β | B2: WACC | D2: MRP | E2: WACC | H2: Project: | I2: Project A
A3: 0.8 | B3: =Inputs!B21*Inputs!B14 + Inputs!B22*(Inputs!B3 + A3*Inputs!B4) + Inputs!B23*Inputs!B10 -> 0.067647059 | D3: 0.03 | E3: =Inputs!B21*Inputs!B14 + Inputs!B22*(Inputs!B3 + Inputs!B5*D3) + Inputs!B23*Inputs!B10 -> 0.065294118
A4: 1 | B4: =Inputs!B21*Inputs!B14 + Inputs!B22*(Inputs!B3 + A4*Inputs!B4) + Inputs!B23*Inputs!B10 -> 0.073529412 | D4: 0.04 | E4: =Inputs!B21*Inputs!B14 + Inputs!B22*(Inputs!B3 + Inputs!B5*D4) + Inputs!B23*Inputs!B10 -> 0.072352941 | H4: WACC → | I4: 0.04 | J4: 0.06 | K4: 0.08 | L4: 0.1 | M4: 0.12 | N4: 0.14
A5: 1.2 | B5: =Inputs!B21*Inputs!B14 + Inputs!B22*(Inputs!B3 + A5*Inputs!B4) + Inputs!B23*Inputs!B10 -> 0.079411765 | D5: 0.05 | E5: =Inputs!B21*Inputs!B14 + Inputs!B22*(Inputs!B3 + Inputs!B5*D5) + Inputs!B23*Inputs!B10 -> 0.079411765 | I5: {=_xlfn.LET(_xlpm.p,$I$2, _xlpm.out, _xlfn.XLOOKUP(_xlpm.p, Projects!$A$2:$A$4, Projects!$B$2:$B$4), _xlpm.cf, _xlfn.XLOOKUP(_xlpm.p, Projects!$A$2:$A$4, Projects!$C$2:$G$4), NPV(I$4, _xlpm.cf)+ _xlpm.out)} -> 54068.908 | J5: {=_xlfn.LET(_xlpm.p,$I$2, _xlpm.out, _xlfn.XLOOKUP(_xlpm.p, Projects!$A$2:$A$4, Projects!$B$2:$B$4), _xlpm.cf, _xlfn.XLOOKUP(_xlpm.p, Projects!$A$2:$A$4, Projects!$C$2:$G$4), NPV(J$4, _xlpm.cf)+ _xlpm.out)} -> 44981.838 | K5: {=_xlfn.LET(_xlpm.p,$I$2, _xlpm.out, _xlfn.XLOOKUP(_xlpm.p, Projects!$A$2:$A$4, Projects!$B$2:$B$4), _xlpm.cf, _xlfn.XLOOKUP(_xlpm.p, Projects!$A$2:$A$4, Projects!$C$2:$G$4), NPV(K$4, _xlpm.cf)+ _xlpm.out)} -> 36679.879 | L5: {=_xlfn.LET(_xlpm.p,$I$2, _xlpm.out, _xlfn.XLOOKUP(_xlpm.p, Projects!$A$2:$A$4, Projects!$B$2:$B$4), _xlpm.cf, _xlfn.XLOOKUP(_xlpm.p, Projects!$A$2:$A$4, Projects!$C$2:$G$4), NPV(L$4, _xlpm.cf)+ _xlpm.out)} -> 29078.677 | M5: {=_xlfn.LET(_xlpm.p,$I$2, _xlpm.out, _xlfn.XLOOKUP(_xlpm.p, Projects!$A$2:$A$4, Projects!$B$2:$B$4), _xlpm.cf, _xlfn.XLOOKUP(_xlpm.p, Projects!$A$2:$A$4, Projects!$C$2:$G$4), NPV(M$4, _xlpm.cf)+ _xlpm.out)} -> 22104.485 | N5: {=_xlfn.LET(_xlpm.p,$I$2, _xlpm.out, _xlfn.XLOOKUP(_xlpm.p, Projects!$A$2:$A$4, Projects!$B$2:$B$4), _xlpm.cf, _xlfn.XLOOKUP(_xlpm.p, Projects!$A$2:$A$4, Projects!$C$2:$G$4), NPV(N$4, _xlpm.cf)+ _xlpm.out)} -> 15692.654
A6: 1.4 | B6: =Inputs!B21*Inputs!B14 + Inputs!B22*(Inputs!B3 + A6*Inputs!B4) + Inputs!B23*Inputs!B10 -> 0.085294118 | D6: 0.06 | E6: =Inputs!B21*Inputs!B14 + Inputs!B22*(Inputs!B3 + Inputs!B5*D6) + Inputs!B23*Inputs!B10 -> 0.086470588
A7: 1.6 | B7: =Inputs!B21*Inputs!B14 + Inputs!B22*(Inputs!B3 + A7*Inputs!B4) + Inputs!B23*Inputs!B10 -> 0.091176471 | D7: 0.07 | E7: =Inputs!B21*Inputs!B14 + Inputs!B22*(Inputs!B3 + Inputs!B5*D7) + Inputs!B23*Inputs!B10 -> 0.093529412

Sheet Dashboard
A1: 📊 Project Decision Dashboard
A3: Select Project: | B3: Project A | E3: WACC: | F3: =Inputs!B25 -> 0.079411765
A6: NPV | B6: =_xlfn.XLOOKUP($B$3, Projects!$A$2:$A$4, Projects!$Y$2:$Y$4) -> 36913.666
A7: IRR | B7: =_xlfn.XLOOKUP($B$3, Projects!$A$2:$A$4, Projects!$Z$2:$Z$4) -> 0.19711108
A8: MIRR | B8: =_xlfn.XLOOKUP($B$3, Projects!$A$2:$A$4, Projects!$AA$2:$AA$4) -> 0.14941407
A9: PI | B9: =_xlfn.XLOOKUP($B$3, Projects!$A$2:$A$4, Projects!$AB$2:$AB$4) -> 1.3691367
A10: Payback (yrs) | B10: =_xlfn.XLOOKUP($B$3, Projects!$A$2:$A$4, Projects!$AC$2:$AC$4) -> 4.25
A11: D-Payback (yrs) | B11: =_xlfn.XLOOKUP($B$3, Projects!$A$2:$A$4, Projects!$AD$2:$AD$4) -> 4.7894515
A12: Decision | B12: =_xlfn.XLOOKUP($B$3, Projects!$A$2:$A$4, Projects!$AE$2:$AE$4) -> ACCEPT
D20: Project | E20: NPV
D21: =Projects!A2 -> Project A | E21: =Projects!Y2 -> 36913.666
D22: =Projects!A3 -> Project B | E22: =Projects!Y3 -> 30447.898
D23: =Projects!A4 -> Project C | E23: =Projects!Y4 -> 27637.826
